{"v":"5.5.8","fr":29.9700012207031,"ip":0,"op":121.000004928431,"w":750,"h":1000,"nm":"sign up page","ddd":0,"assets":[{"id":"comp_0","layers":[{"ddd":0,"ind":1,"ty":4,"nm":"Shape Layer 3","td":1,"sr":1,"ks":{"o":{"a":0,"k":100,"ix":11},"r":{"a":0,"k":0,"ix":10},"p":{"a":0,"k":[379,879,0],"ix":2},"a":{"a":0,"k":[0,0,0],"ix":1},"s":{"a":0,"k":[100,100,100],"ix":6}},"ao":0,"shapes":[{"ty":"gr","it":[{"ind":0,"ty":"sh","ix":1,"ks":{"a":0,"k":{"i":[[0,0],[0,0],[0,0],[0,0],[0,0]],"o":[[0,0],[0,0],[0,0],[0,0],[0,0]],"v":[[-23.5,-543.5],[-87.5,-557.5],[-127.5,-498],[-65.5,-475],[-45.5,-507]],"c":true},"ix":2},"nm":"Path 1","mn":"ADBE Vector Shape - Group","hd":false},{"ty":"st","c":{"a":0,"k":[0.098039223166,0.360784313725,0.529411764706,1],"ix":3},"o":{"a":0,"k":100,"ix":4},"w":{"a":0,"k":0,"ix":5},"lc":1,"lj":1,"ml":4,"bm":0,"nm":"Stroke 1","mn":"ADBE Vector Graphic - Stroke","hd":false},{"ty":"fl","c":{"a":0,"k":[0.835294117647,0.835294117647,0.835294117647,1],"ix":4},"o":{"a":0,"k":100,"ix":5},"r":1,"bm":0,"nm":"Fill 1","mn":"ADBE Vector Graphic - Fill","hd":false},{"ty":"tr","p":{"a":0,"k":[0,0],"ix":2},"a":{"a":0,"k":[0,0],"ix":1},"s":{"a":0,"k":[100,100],"ix":3},"r":{"a":0,"k":0,"ix":6},"o":{"a":0,"k":100,"ix":7},"sk":{"a":0,"k":0,"ix":4},"sa":{"a":0,"k":0,"ix":5},"nm":"Transform"}],"nm":"Shape 1","np":3,"cix":2,"bm":0,"ix":1,"mn":"ADBE Vector Group","hd":false}],"ip":0,"op":917.000037350176,"st":0,"bm":0},{"ddd":0,"ind":2,"ty":4,"nm":"blue line","tt":2,"sr":1,"ks":{"o":{"a":0,"k":100,"ix":11},"r":{"a":0,"k":212,"ix":10},"p":{"a":0,"k":[313.192,397.234,0],"ix":2},"a":{"a":0,"k":[32.192,-459.766,0],"ix":1},"s":{"a":0,"k":[100,100,100],"ix":6}},"ao":0,"shapes":[{"ty":"gr","it":[{"ind":0,"ty":"sh","ix":1,"ks":{"a":0,"k":{"i":[[0,0],[-58.944,-267.614],[12.722,-65.912],[50.807,-32.841],[57.166,22.893],[13.72,52.569],[-21.133,22.816],[-32.622,5.142],[-23.791,-11.266],[-8.012,-15.104],[-1.897,-12.585]],"o":[[43.887,177.357],[14.439,65.557],[-11.465,59.4],[-51.716,33.429],[-50.436,-20.198],[-7.853,-30.092],[22.441,-24.229],[26.003,-4.099],[15.452,7.317],[8.778,16.549],[0,0]],"v":[[-27.879,-1464.501],[162.726,-664.815],[192.137,-465.588],[94.716,-312.461],[-87.905,-284.569],[-176.79,-421.189],[-146.6,-509.468],[-56.621,-550.934],[20.9,-535.87],[55.38,-497.897],[69.848,-443.591]],"c":false},"ix":2},"nm":"Path 1","mn":"ADBE Vector Shape - Group","hd":false},{"ty":"st","c":{"a":0,"k":[0.098039223166,0.360784313725,0.529411764706,1],"ix":3},"o":{"a":0,"k":100,"ix":4},"w":{"a":0,"k":18,"ix":5},"lc":2,"lj":1,"ml":4,"bm":0,"nm":"Stroke 1","mn":"ADBE Vector Graphic - Stroke","hd":false},{"ty":"tr","p":{"a":0,"k":[0,0],"ix":2},"a":{"a":0,"k":[0,0],"ix":1},"s":{"a":0,"k":[100,100],"ix":3},"r":{"a":0,"k":0,"ix":6},"o":{"a":0,"k":100,"ix":7},"sk":{"a":0,"k":0,"ix":4},"sa":{"a":0,"k":0,"ix":5},"nm":"Transform"}],"nm":"Shape 1","np":2,"cix":2,"bm":0,"ix":1,"mn":"ADBE Vector Group","hd":false},{"ty":"tm","s":{"a":0,"k":0,"ix":1},"e":{"a":0,"k":8,"ix":2},"o":{"a":1,"k":[{"i":{"x":[0.833],"y":[1]},"o":{"x":[0.333],"y":[0]},"t":4,"s":[23]},{"t":68.0000027696968,"s":[363]}],"ix":3},"m":1,"ix":2,"nm":"Trim Paths 1","mn":"ADBE Vector Filter - Trim","hd":false}],"ip":0,"op":71.0000028918893,"st":0,"bm":0},{"ddd":0,"ind":3,"ty":4,"nm":"Shape Layer 11","td":1,"sr":1,"ks":{"o":{"a":0,"k":100,"ix":11},"r":{"a":0,"k":0,"ix":10},"p":{"a":0,"k":[375,667,0],"ix":2},"a":{"a":0,"k":[0,0,0],"ix":1},"s":{"a":0,"k":[100,100,100],"ix":6}},"ao":0,"shapes":[{"ty":"gr","it":[{"ind":0,"ty":"sh","ix":1,"ks":{"a":0,"k":{"i":[[0,0],[0,0],[0,0],[0,0]],"o":[[0,0],[0,0],[0,0],[0,0]],"v":[[-87.25,-252.5],[-116.5,-238.25],[-111.5,-204.75],[-76,-203]],"c":true},"ix":2},"nm":"Path 1","mn":"ADBE Vector Shape - Group","hd":false},{"ty":"fl","c":{"a":0,"k":[1,1,1,1],"ix":4},"o":{"a":0,"k":100,"ix":5},"r":1,"bm":0,"nm":"Fill 1","mn":"ADBE Vector Graphic - Fill","hd":false},{"ty":"tr","p":{"a":0,"k":[0,0],"ix":2},"a":{"a":0,"k":[0,0],"ix":1},"s":{"a":0,"k":[100,100],"ix":3},"r":{"a":0,"k":0,"ix":6},"o":{"a":0,"k":100,"ix":7},"sk":{"a":0,"k":0,"ix":4},"sa":{"a":0,"k":0,"ix":5},"nm":"Transform"}],"nm":"Shape 2","np":3,"cix":2,"bm":0,"ix":1,"mn":"ADBE Vector Group","hd":false},{"ty":"gr","it":[{"ind":0,"ty":"sh","ix":1,"ks":{"a":0,"k":{"i":[[12.162,3.352],[12.316,-22.33],[0,0],[0,0]],"o":[[-24.585,-6.776],[-11.27,20.433],[0,0],[0,0]],"v":[[-37.5,-385.25],[-114,-386],[-64.25,-336.75],[-11.5,-357.75]],"c":true},"ix":2},"nm":"Path 1","mn":"ADBE Vector Shape - Group","hd":false},{"ty":"fl","c":{"a":0,"k":[1,1,1,1],"ix":4},"o":{"a":0,"k":100,"ix":5},"r":1,"bm":0,"nm":"Fill 1","mn":"ADBE Vector Graphic - Fill","hd":false},{"ty":"tr","p":{"a":0,"k":[0,0],"ix":2},"a":{"a":0,"k":[0,0],"ix":1},"s":{"a":0,"k":[100,100],"ix":3},"r":{"a":0,"k":0,"ix":6},"o":{"a":0,"k":100,"ix":7},"sk":{"a":0,"k":0,"ix":4},"sa":{"a":0,"k":0,"ix":5},"nm":"Transform"}],"nm":"Shape 1","np":3,"cix":2,"bm":0,"ix":2,"mn":"ADBE Vector Group","hd":false}],"ip":0,"op":917.000037350176,"st":0,"bm":0},{"ddd":0,"ind":4,"ty":4,"nm":"blue line 3","tt":2,"sr":1,"ks":{"o":{"a":0,"k":100,"ix":11},"r":{"a":0,"k":0,"ix":10},"p":{"a":0,"k":[375,667,0],"ix":2},"a":{"a":0,"k":[0,0,0],"ix":1},"s":{"a":0,"k":[100,100,100],"ix":6}},"ao":0,"shapes":[{"ty":"gr","it":[{"ind":0,"ty":"sh","ix":1,"ks":{"a":0,"k":{"i":[[0,0],[166.586,246.188],[123.843,-39.405],[-6.098,-84.257],[-47.43,-5.903],[0,0],[2.689,20.158],[5.973,5.422],[13.544,8.894]],"o":[[-27.805,-203.271],[-72.832,-107.635],[-80.501,25.614],[3.45,47.671],[38.759,4.824],[0,0],[-1.067,-7.996],[-17.923,-16.271],[0,0]],"v":[[477,415],[227,-441],[-155,-519],[-257,-287],[-133,-215],[-24,-258],[-23,-319],[-34.945,-340.047],[-93.5,-383]],"c":false},"ix":2},"nm":"Path 1","mn":"ADBE Vector Shape - Group","hd":false},{"ty":"st","c":{"a":0,"k":[0.098039223166,0.360784313725,0.529411764706,1],"ix":3},"o":{"a":0,"k":100,"ix":4},"w":{"a":0,"k":20,"ix":5},"lc":2,"lj":1,"ml":4,"bm":0,"nm":"Stroke 1","mn":"ADBE Vector Graphic - Stroke","hd":false},{"ty":"tr","p":{"a":0,"k":[0,0],"ix":2},"a":{"a":0,"k":[0,0],"ix":1},"s":{"a":0,"k":[100,100],"ix":3},"r":{"a":0,"k":0,"ix":6},"o":{"a":0,"k":100,"ix":7},"sk":{"a":0,"k":0,"ix":4},"sa":{"a":0,"k":0,"ix":5},"nm":"Transform"}],"nm":"Shape 1","np":3,"cix":2,"bm":0,"ix":1,"mn":"ADBE Vector Group","hd":false},{"ty":"tm","s":{"a":0,"k":0,"ix":1},"e":{"a":0,"k":8,"ix":2},"o":{"a":1,"k":[{"i":{"x":[0.833],"y":[1]},"o":{"x":[0.167],"y":[0]},"t":17,"s":[0]},{"t":66.0000026882351,"s":[350]}],"ix":3},"m":1,"ix":2,"nm":"Trim Paths 1","mn":"ADBE Vector Filter - Trim","hd":false}],"ip":0,"op":76.0000030955435,"st":0,"bm":0},{"ddd":0,"ind":5,"ty":4,"nm":"Shape Layer 9","td":1,"sr":1,"ks":{"o":{"a":0,"k":100,"ix":11},"r":{"a":0,"k":0,"ix":10},"p":{"a":0,"k":[375,667,0],"ix":2},"a":{"a":0,"k":[0,0,0],"ix":1},"s":{"a":0,"k":[100,100,100],"ix":6}},"ao":0,"shapes":[{"ty":"gr","it":[{"ind":0,"ty":"sh","ix":1,"ks":{"a":0,"k":{"i":[[16.514,-2.747],[-9.809,-23.158],[0,0],[0,0]],"o":[[-24.809,4.126],[11.441,27.01],[0,0],[0,0]],"v":[[-110,-345.25],[-180.5,-318.375],[-93.375,-306],[-60.25,-338.375]],"c":true},"ix":2},"nm":"Path 1","mn":"ADBE Vector Shape - Group","hd":false},{"ty":"fl","c":{"a":0,"k":[1,1,1,1],"ix":4},"o":{"a":0,"k":100,"ix":5},"r":1,"bm":0,"nm":"Fill 1","mn":"ADBE Vector Graphic - Fill","hd":false},{"ty":"tr","p":{"a":0,"k":[0,0],"ix":2},"a":{"a":0,"k":[0,0],"ix":1},"s":{"a":0,"k":[100,100],"ix":3},"r":{"a":0,"k":0,"ix":6},"o":{"a":0,"k":100,"ix":7},"sk":{"a":0,"k":0,"ix":4},"sa":{"a":0,"k":0,"ix":5},"nm":"Transform"}],"nm":"Shape 2","np":3,"cix":2,"bm":0,"ix":1,"mn":"ADBE Vector Group","hd":false},{"ty":"gr","it":[{"ind":0,"ty":"sh","ix":1,"ks":{"a":0,"k":{"i":[[0,0],[0,0],[0,0],[0,0]],"o":[[0,0],[0,0],[0,0],[0,0]],"v":[[-77.25,-287],[-107,-283.25],[-122.75,-216.5],[-84,-232.5]],"c":true},"ix":2},"nm":"Path 1","mn":"ADBE Vector Shape - Group","hd":false},{"ty":"fl","c":{"a":0,"k":[1,1,1,1],"ix":4},"o":{"a":0,"k":100,"ix":5},"r":1,"bm":0,"nm":"Fill 1","mn":"ADBE Vector Graphic - Fill","hd":false},{"ty":"tr","p":{"a":0,"k":[0,0],"ix":2},"a":{"a":0,"k":[0,0],"ix":1},"s":{"a":0,"k":[100,100],"ix":3},"r":{"a":0,"k":0,"ix":6},"o":{"a":0,"k":100,"ix":7},"sk":{"a":0,"k":0,"ix":4},"sa":{"a":0,"k":0,"ix":5},"nm":"Transform"}],"nm":"Shape 1","np":3,"cix":2,"bm":0,"ix":2,"mn":"ADBE Vector Group","hd":false}],"ip":0,"op":917.000037350176,"st":0,"bm":0},{"ddd":0,"ind":6,"ty":4,"nm":"blue line 2","tt":2,"sr":1,"ks":{"o":{"a":0,"k":100,"ix":11},"r":{"a":0,"k":0,"ix":10},"p":{"a":0,"k":[375,667,0],"ix":2},"a":{"a":0,"k":[0,0,0],"ix":1},"s":{"a":0,"k":[100,100,100],"ix":6}},"ao":0,"shapes":[{"ty":"gr","it":[{"ind":0,"ty":"sh","ix":1,"ks":{"a":0,"k":{"i":[[0,0],[170.22,185.531],[71.62,-17.404],[-0.781,-40.116],[-28.974,-5.381],[0,0],[11.522,6.679],[14.944,-3.344]],"o":[[-75.927,-152.156],[-49.828,-54.31],[-38.989,9.475],[0.574,29.464],[24.708,4.589],[0,0],[-18.169,-10.532],[0,0]],"v":[[489,269.001],[91,-373],[-128,-403.5],[-195,-303.5],[-125,-249.5],[-55,-277.5],[-61,-317],[-124,-317.5]],"c":false},"ix":2},"nm":"Path 1","mn":"ADBE Vector Shape - Group","hd":false},{"ty":"st","c":{"a":0,"k":[0.454901990704,0.796078491211,0.90588241278,1],"ix":3},"o":{"a":0,"k":100,"ix":4},"w":{"a":0,"k":20,"ix":5},"lc":2,"lj":1,"ml":4,"bm":0,"nm":"Stroke 1","mn":"ADBE Vector Graphic - Stroke","hd":false},{"ty":"tr","p":{"a":0,"k":[0,0],"ix":2},"a":{"a":0,"k":[0,0],"ix":1},"s":{"a":0,"k":[100,100],"ix":3},"r":{"a":0,"k":0,"ix":6},"o":{"a":0,"k":100,"ix":7},"sk":{"a":0,"k":0,"ix":4},"sa":{"a":0,"k":0,"ix":5},"nm":"Transform"}],"nm":"Shape 1","np":3,"cix":2,"bm":0,"ix":1,"mn":"ADBE Vector Group","hd":false},{"ty":"tm","s":{"a":0,"k":0,"ix":1},"e":{"a":0,"k":7,"ix":2},"o":{"a":1,"k":[{"i":{"x":[0.833],"y":[1]},"o":{"x":[0.333],"y":[0]},"t":14,"s":[29]},{"t":66.0000026882351,"s":[361]}],"ix":3},"m":1,"ix":2,"nm":"Trim Paths 1","mn":"ADBE Vector Filter - Trim","hd":false}],"ip":0,"op":81.0000032991976,"st":0,"bm":0},{"ddd":0,"ind":7,"ty":4,"nm":"blue6","sr":1,"ks":{"o":{"a":1,"k":[{"i":{"x":[0.833],"y":[1]},"o":{"x":[0.333],"y":[0]},"t":59,"s":[0]},{"t":61.0000024845809,"s":[100]}],"ix":11},"r":{"a":0,"k":0,"ix":10},"p":{"a":0,"k":[278.979,428.15,0],"ix":2},"a":{"a":0,"k":[10.397,76.501,0],"ix":1},"s":{"a":0,"k":[151.293,151.293,100],"ix":6}},"ao":0,"shapes":[{"ty":"gr","it":[{"ind":0,"ty":"sh","ix":1,"ks":{"a":0,"k":{"i":[[-0.283,0.168],[-0.009,-1.082],[-0.103,-2.766],[0.31,-0.913],[0.417,-1.206],[0.298,-1.101],[0.197,-1.155],[0.205,-2.086],[0.046,-1.94],[-0.392,-2.433],[-0.517,-2.372],[-0.504,-1.659],[-1.557,-3.047],[-0.257,-0.539],[0.106,-0.185],[1.477,-2.539],[0.737,-1.285],[0.112,-0.165],[1.562,2.928],[1.302,4.325],[0.526,2.459],[0.268,2.1],[0.041,1.355],[-0.069,2.702],[-0.274,1.879],[-0.503,2.377],[-1.572,3.719],[-0.454,0.333],[-2.254,1.611],[-1.156,0.831]],"o":[[0,1.219],[0.022,2.768],[0.038,1.036],[-0.411,1.208],[-0.373,1.079],[-0.306,1.132],[-0.353,2.069],[-0.19,1.928],[-0.059,2.462],[0.387,2.399],[0.368,1.689],[0.998,3.286],[0.272,0.533],[0.096,0.202],[-1.462,2.547],[-0.745,1.28],[-0.08,0.14],[-1.921,-2.752],[-2.128,-3.989],[-0.725,-2.409],[-0.442,-2.066],[-0.172,-1.345],[-0.081,-2.703],[0.049,-1.895],[0.351,-2.404],[0.836,-3.953],[0.212,-0.502],[2.234,-1.638],[1.158,-0.828],[0.133,-0.096]],"v":[[17.45,36.514],[17.452,39.897],[17.556,48.201],[16.903,51.023],[15.587,54.619],[14.561,57.885],[13.779,61.316],[12.855,67.545],[12.607,73.36],[13.066,80.713],[14.343,87.89],[15.806,92.878],[19.83,102.296],[20.716,103.859],[20.72,104.584],[16.286,112.2],[14.079,116.055],[13.786,116.489],[8.531,108.021],[3.32,95.576],[1.407,88.272],[0.465,81.992],[0.125,77.935],[0.025,69.822],[0.585,64.149],[1.843,56.966],[5.526,45.469],[6.665,44.186],[13.423,39.35],[16.886,36.852]],"c":true},"ix":2},"nm":"Path 1","mn":"ADBE Vector Shape - Group","hd":false},{"ty":"st","c":{"a":0,"k":[1,1,1,1],"ix":3},"o":{"a":0,"k":100,"ix":4},"w":{"a":0,"k":0,"ix":5},"lc":1,"lj":1,"ml":4,"bm":0,"nm":"Stroke 1","mn":"ADBE Vector Graphic - Stroke","hd":false},{"ty":"fl","c":{"a":1,"k":[{"i":{"x":[0.667],"y":[1]},"o":{"x":[0.333],"y":[0]},"t":70,"s":[0.098039223166,0.360784313725,0.529411764706,1]},{"t":84.0000034213901,"s":[0.007843137719,0.450980424881,0.207843154669,1]}],"ix":4},"o":{"a":0,"k":100,"ix":5},"r":1,"bm":0,"nm":"Fill 1","mn":"ADBE Vector Graphic - Fill","hd":false},{"ty":"tr","p":{"a":0,"k":[0,0],"ix":2},"a":{"a":0,"k":[0,0],"ix":1},"s":{"a":0,"k":[100,100],"ix":3},"r":{"a":0,"k":0,"ix":6},"o":{"a":0,"k":100,"ix":7},"sk":{"a":0,"k":0,"ix":4},"sa":{"a":0,"k":0,"ix":5},"nm":"Transform"}],"nm":"Shape 1","np":3,"cix":2,"bm":0,"ix":1,"mn":"ADBE Vector Group","hd":false}],"ip":0,"op":688.000028022814,"st":0,"bm":0},{"ddd":0,"ind":8,"ty":4,"nm":"blue5","sr":1,"ks":{"o":{"a":1,"k":[{"i":{"x":[0.667],"y":[1]},"o":{"x":[0.167],"y":[0]},"t":58,"s":[0]},{"t":59.0000024031193,"s":[100]}],"ix":11},"r":{"a":0,"k":0,"ix":10},"p":{"a":0,"k":[312.212,372.342,0],"ix":2},"a":{"a":0,"k":[31.29,40.032,0],"ix":1},"s":{"a":0,"k":[151.293,151.293,100],"ix":6}},"ao":0,"shapes":[{"ty":"gr","it":[{"ind":0,"ty":"sh","ix":1,"ks":{"a":0,"k":{"i":[[0.849,0.088],[-1.083,1.197],[-1.415,1.319],[-1.87,1.585],[-0.184,-0.012],[-2.309,-1.189],[-1.327,-2.151],[-0.425,-2.634],[-0.011,-1.628],[0.042,-2.17],[0.038,-1.712],[0.043,-1.769],[0.002,-1.292],[0.265,-0.154],[2.701,-1.57],[2.677,-1.536],[2.627,-0.633],[0.636,-0.185],[-0.095,0.734],[-0.251,1.183],[-0.497,1.937],[-0.418,1.109],[-0.31,0.18],[-2.763,1.612],[-0.008,0.193],[-0.042,1.559],[-0.043,1.253],[0.08,0.957],[2.505,1.624],[1.239,0.067],[2.219,0.096]],"o":[[1.096,-1.288],[1.3,-1.437],[1.791,-1.67],[0.142,-0.121],[2.56,0.169],[2.262,1.165],[1.411,2.286],[0.258,1.598],[0.015,2.17],[-0.033,1.712],[-0.039,1.769],[-0.032,1.292],[0,0.365],[-2.704,1.565],[-2.668,1.55],[-2.297,1.318],[-0.523,0.126],[0.049,-0.815],[0.155,-1.201],[0.414,-1.956],[0.295,-1.148],[0.113,-0.3],[2.765,-1.609],[0.167,-0.097],[0.064,-1.558],[0.034,-1.253],[0.033,-0.967],[-0.236,-2.822],[-1.061,-0.688],[-2.218,-0.12],[-0.745,-0.032]],"v":[[15.189,28.676],[18.385,24.934],[22.389,20.721],[27.96,15.924],[28.521,15.73],[35.887,17.534],[41.233,22.57],[43.968,29.996],[44.223,34.872],[44.12,41.382],[44.007,46.518],[43.891,51.825],[43.792,55.699],[43.374,56.411],[35.259,61.099],[27.264,65.767],[20.106,69.179],[18.434,69.661],[18.58,67.365],[19.149,63.778],[20.518,57.935],[21.598,54.544],[22.406,53.827],[30.712,49.022],[31.045,48.469],[31.175,43.792],[31.29,40.032],[31.384,37.133],[27.694,30.204],[24.184,29.161],[17.525,28.912]],"c":true},"ix":2},"nm":"Path 1","mn":"ADBE Vector Shape - Group","hd":false},{"ty":"st","c":{"a":0,"k":[1,1,1,1],"ix":3},"o":{"a":0,"k":100,"ix":4},"w":{"a":0,"k":0,"ix":5},"lc":1,"lj":1,"ml":4,"bm":0,"nm":"Stroke 1","mn":"ADBE Vector Graphic - Stroke","hd":false},{"ty":"fl","c":{"a":1,"k":[{"i":{"x":[0.667],"y":[1]},"o":{"x":[0.333],"y":[0]},"t":77,"s":[0.454901990704,0.796078491211,0.90588241278,1]},{"t":86.0000035028518,"s":[0.643137276173,0.811764776707,0.215686291456,1]}],"ix":4},"o":{"a":0,"k":100,"ix":5},"r":1,"bm":0,"nm":"Fill 1","mn":"ADBE Vector Graphic - Fill","hd":false},{"ty":"tr","p":{"a":0,"k":[0,0],"ix":2},"a":{"a":0,"k":[0,0],"ix":1},"s":{"a":0,"k":[100,100],"ix":3},"r":{"a":0,"k":0,"ix":6},"o":{"a":0,"k":100,"ix":7},"sk":{"a":0,"k":0,"ix":4},"sa":{"a":0,"k":0,"ix":5},"nm":"Transform"}],"nm":"Shape 1","np":3,"cix":2,"bm":0,"ix":1,"mn":"ADBE Vector Group","hd":false}],"ip":0,"op":2756.241112264,"st":0,"bm":0},{"ddd":0,"ind":9,"ty":4,"nm":"blue4","sr":1,"ks":{"o":{"a":1,"k":[{"i":{"x":[0.833],"y":[1]},"o":{"x":[0.167],"y":[0]},"t":58,"s":[0]},{"t":59.0000024031193,"s":[100]}],"ix":11},"r":{"a":0,"k":0,"ix":10},"p":{"a":0,"k":[326.834,383.892,0],"ix":2},"a":{"a":0,"k":[41.958,47.22,0],"ix":1},"s":{"a":0,"k":[151.293,151.293,100],"ix":6}},"ao":0,"shapes":[{"ty":"gr","it":[{"ind":0,"ty":"sh","ix":1,"ks":{"a":0,"k":{"i":[[0.073,0.532],[-1.36,0.383],[-1.969,1.147],[-1.587,0.918],[-2.042,1.176],[-1.877,1.089],[-1.744,1.057],[-0.15,0.636],[-0.006,0.566],[-0.016,1.413],[-0.042,2.533],[-0.037,2.075],[-0.048,2.17],[-0.046,0.833],[0.646,2.424],[1.818,2.489],[3.315,1.224],[0.634,0.239],[-1.437,0.658],[-1.702,0.614],[-2.308,0.739],[-0.1,-0.099],[-1.143,-1.286],[-1.019,-2.221],[-0.549,-2.757],[-0.231,-1.535],[0,-0.535],[0.016,-1.432],[0.041,-2.552],[0.037,-2.151],[0.039,-2.246],[0.037,-2.132],[0.048,-2.303],[0.068,-0.831],[0.154,-0.093],[1.405,-0.821],[1.907,-1.111],[1.726,-1.012],[1.598,-0.936],[1.726,-1.013],[2.025,-1.276],[3.995,-1.095],[0.111,0.42],[0.534,2.285],[0.225,1.476]],"o":[[1.376,-0.419],[2.225,-0.626],[1.584,-0.923],[2.04,-1.18],[1.88,-1.083],[1.764,-1.023],[0.467,-0.283],[0.128,-0.544],[0.016,-1.413],[0.028,-2.533],[0.034,-2.075],[0.039,-2.17],[0.018,-0.833],[0.139,-2.532],[-0.79,-2.964],[-2.07,-2.835],[-0.526,-0.194],[1.488,-0.757],[1.646,-0.753],[2.279,-0.822],[0.128,-0.041],[1.222,1.214],[1.632,1.836],[1.171,2.553],[0.304,1.522],[0.079,0.523],[0.001,1.433],[-0.028,2.552],[-0.035,2.151],[-0.039,2.246],[-0.037,2.132],[-0.04,2.304],[-0.017,0.833],[-0.015,0.183],[-1.391,0.844],[-1.905,1.114],[-1.729,1.007],[-1.598,0.936],[-1.726,1.012],[-2.065,1.212],[-3.505,2.209],[-0.457,0.125],[-0.599,-2.27],[-0.339,-1.45],[-0.085,-0.553]],"v":[[18.454,78.318],[22.535,77.083],[28.673,74.116],[33.423,71.343],[39.553,67.82],[45.188,64.563],[50.468,61.473],[51.786,60.49],[51.914,58.797],[51.922,54.557],[52.035,46.958],[52.149,40.734],[52.267,34.224],[52.379,31.725],[51.435,24.303],[47.65,16.036],[39.59,9.892],[37.907,9.257],[42.221,7.078],[47.234,4.984],[54.142,2.715],[54.598,2.841],[58.223,6.523],[62.032,12.734],[64.633,20.701],[65.422,25.291],[65.44,26.893],[65.438,31.191],[65.325,38.847],[65.211,45.3],[65.096,52.039],[64.982,58.435],[64.864,65.346],[64.74,67.844],[64.435,68.361],[60.232,70.846],[54.512,74.178],[49.326,77.202],[44.539,80.023],[39.354,83.048],[33.174,86.707],[21.949,91.702],[21.194,91.188],[19.388,84.38],[18.681,79.959]],"c":true},"ix":2},"nm":"Path 1","mn":"ADBE Vector Shape - Group","hd":false},{"ty":"st","c":{"a":0,"k":[1,1,1,1],"ix":3},"o":{"a":0,"k":100,"ix":4},"w":{"a":0,"k":0,"ix":5},"lc":1,"lj":1,"ml":4,"bm":0,"nm":"Stroke 1","mn":"ADBE Vector Graphic - Stroke","hd":false},{"ty":"fl","c":{"a":1,"k":[{"i":{"x":[0.667],"y":[1]},"o":{"x":[0.333],"y":[0]},"t":84,"s":[0.098039223166,0.360784313725,0.529411764706,1]},{"t":93.0000037879676,"s":[0.007843137719,0.450980424881,0.207843154669,1]}],"ix":4},"o":{"a":0,"k":100,"ix":5},"r":1,"bm":0,"nm":"Fill 1","mn":"ADBE Vector Graphic - Fill","hd":false},{"ty":"tr","p":{"a":0,"k":[0,0],"ix":2},"a":{"a":0,"k":[0,0],"ix":1},"s":{"a":0,"k":[100,100],"ix":3},"r":{"a":0,"k":0,"ix":6},"o":{"a":0,"k":100,"ix":7},"sk":{"a":0,"k":0,"ix":4},"sa":{"a":0,"k":0,"ix":5},"nm":"Transform"}],"nm":"Shape 1","np":3,"cix":2,"bm":0,"ix":1,"mn":"ADBE Vector Group","hd":false}],"ip":0,"op":2756.241112264,"st":0,"bm":0},{"ddd":0,"ind":10,"ty":4,"nm":"Shape Layer 7","td":1,"sr":1,"ks":{"o":{"a":0,"k":100,"ix":11},"r":{"a":0,"k":0,"ix":10},"p":{"a":0,"k":[375,667,0],"ix":2},"a":{"a":0,"k":[0,0,0],"ix":1},"s":{"a":0,"k":[100,100,100],"ix":6}},"ao":0,"shapes":[{"ty":"gr","it":[{"ind":0,"ty":"sh","ix":1,"ks":{"a":0,"k":{"i":[[12.451,-2.359],[0,0],[0,0],[-12.005,14.311],[6.493,14.284]],"o":[[-15.6,2.956],[0,0],[0,0],[10.084,-12.021],[-5.244,-11.537]],"v":[[136.25,-331.25],[99.25,-301.25],[113.25,-246.5],[165,-268],[170.5,-314.75]],"c":true},"ix":2},"nm":"Path 1","mn":"ADBE Vector Shape - Group","hd":false},{"ty":"st","c":{"a":0,"k":[1,0.713725490196,0.254901960784,1],"ix":3},"o":{"a":0,"k":100,"ix":4},"w":{"a":0,"k":0,"ix":5},"lc":1,"lj":1,"ml":4,"bm":0,"nm":"Stroke 1","mn":"ADBE Vector Graphic - Stroke","hd":false},{"ty":"fl","c":{"a":0,"k":[1,1,1,1],"ix":4},"o":{"a":0,"k":100,"ix":5},"r":1,"bm":0,"nm":"Fill 1","mn":"ADBE Vector Graphic - Fill","hd":false},{"ty":"tr","p":{"a":0,"k":[0,0],"ix":2},"a":{"a":0,"k":[0,0],"ix":1},"s":{"a":0,"k":[100,100],"ix":3},"r":{"a":0,"k":0,"ix":6},"o":{"a":0,"k":100,"ix":7},"sk":{"a":0,"k":0,"ix":4},"sa":{"a":0,"k":0,"ix":5},"nm":"Transform"}],"nm":"Shape 2","np":3,"cix":2,"bm":0,"ix":1,"mn":"ADBE Vector Group","hd":false},{"ty":"gr","it":[{"ind":0,"ty":"sh","ix":1,"ks":{"a":0,"k":{"i":[[0,0],[0,0],[0,0],[0,0]],"o":[[0,0],[0,0],[0,0],[0,0]],"v":[[55.5,-354.25],[42.25,-314.625],[70.08,-289.867],[78.25,-328.75]],"c":true},"ix":2},"nm":"Path 1","mn":"ADBE Vector Shape - Group","hd":false},{"ty":"st","c":{"a":0,"k":[1,0.713725490196,0.254901960784,1],"ix":3},"o":{"a":0,"k":100,"ix":4},"w":{"a":0,"k":0,"ix":5},"lc":1,"lj":1,"ml":4,"bm":0,"nm":"Stroke 1","mn":"ADBE Vector Graphic - Stroke","hd":false},{"ty":"fl","c":{"a":0,"k":[1,1,1,1],"ix":4},"o":{"a":0,"k":100,"ix":5},"r":1,"bm":0,"nm":"Fill 1","mn":"ADBE Vector Graphic - Fill","hd":false},{"ty":"tr","p":{"a":0,"k":[0,0],"ix":2},"a":{"a":0,"k":[0,0],"ix":1},"s":{"a":0,"k":[100,100],"ix":3},"r":{"a":0,"k":0,"ix":6},"o":{"a":0,"k":100,"ix":7},"sk":{"a":0,"k":0,"ix":4},"sa":{"a":0,"k":0,"ix":5},"nm":"Transform"}],"nm":"Shape 1","np":3,"cix":2,"bm":0,"ix":2,"mn":"ADBE Vector Group","hd":false}],"ip":0,"op":917.000037350176,"st":0,"bm":0},{"ddd":0,"ind":11,"ty":4,"nm":"orange line 3","tt":2,"sr":1,"ks":{"o":{"a":0,"k":100,"ix":11},"r":{"a":0,"k":0,"ix":10},"p":{"a":0,"k":[375,667,0],"ix":2},"a":{"a":0,"k":[0,0,0],"ix":1},"s":{"a":0,"k":[100,100,100],"ix":6}},"ao":0,"shapes":[{"ty":"gr","it":[{"ind":0,"ty":"sh","ix":1,"ks":{"a":0,"k":{"i":[[0,0],[22.77,-195.821],[-57.264,-9.678],[-41.884,46.139],[19.837,36.811],[41.475,-11.108],[0,0],[0,0],[-11.606,6.274],[-6.069,15.511]],"o":[[-57.743,120.726],[-6.708,57.688],[61.443,10.385],[28.106,-30.962],[-20.369,-37.798],[-45.383,12.154],[0,0],[0,0],[20.292,-10.969],[0,0]],"v":[[151,-843],[-45,-285],[71,-155],[239,-237],[258,-361],[142,-417],[54.5,-306.5],[55,-272.5],[90.5,-255],[129,-312.5]],"c":false},"ix":2},"nm":"Path 1","mn":"ADBE Vector Shape - Group","hd":false},{"ty":"st","c":{"a":0,"k":[1,0.713725490196,0.254901960784,1],"ix":3},"o":{"a":0,"k":100,"ix":4},"w":{"a":0,"k":20,"ix":5},"lc":2,"lj":1,"ml":4,"bm":0,"nm":"Stroke 1","mn":"ADBE Vector Graphic - Stroke","hd":false},{"ty":"tr","p":{"a":0,"k":[0,0],"ix":2},"a":{"a":0,"k":[0,0],"ix":1},"s":{"a":0,"k":[100,100],"ix":3},"r":{"a":0,"k":0,"ix":6},"o":{"a":0,"k":100,"ix":7},"sk":{"a":0,"k":0,"ix":4},"sa":{"a":0,"k":0,"ix":5},"nm":"Transform"}],"nm":"Shape 1","np":3,"cix":2,"bm":0,"ix":1,"mn":"ADBE Vector Group","hd":false},{"ty":"tm","s":{"a":0,"k":0,"ix":1},"e":{"a":0,"k":7,"ix":2},"o":{"a":1,"k":[{"i":{"x":[0.833],"y":[1]},"o":{"x":[0.333],"y":[0]},"t":25,"s":[-4]},{"t":66.0000026882351,"s":[375]}],"ix":3},"m":1,"ix":2,"nm":"Trim Paths 1","mn":"ADBE Vector Filter - Trim","hd":false}],"ip":0,"op":74.0000030140818,"st":0,"bm":0},{"ddd":0,"ind":12,"ty":4,"nm":"Shape Layer 6","td":1,"sr":1,"ks":{"o":{"a":0,"k":100,"ix":11},"r":{"a":0,"k":0,"ix":10},"p":{"a":0,"k":[375,667,0],"ix":2},"a":{"a":0,"k":[0,0,0],"ix":1},"s":{"a":0,"k":[100,100,100],"ix":6}},"ao":0,"shapes":[{"ty":"gr","it":[{"ind":0,"ty":"sh","ix":1,"ks":{"a":0,"k":{"i":[[6.047,2.687],[17.168,-4.458],[0,0],[0,0],[-2.717,7.391]],"o":[[-16.209,-7.204],[-8.549,2.22],[0,0],[0,0],[2.283,-6.211]],"v":[[60.25,-349],[7.5,-356],[-4.25,-332.25],[47.75,-315],[66,-330]],"c":true},"ix":2},"nm":"Path 1","mn":"ADBE Vector Shape - Group","hd":false},{"ty":"st","c":{"a":0,"k":[0.749019607843,0.407843167174,0.090196078431,1],"ix":3},"o":{"a":0,"k":100,"ix":4},"w":{"a":0,"k":0,"ix":5},"lc":1,"lj":1,"ml":4,"bm":0,"nm":"Stroke 1","mn":"ADBE Vector Graphic - Stroke","hd":false},{"ty":"fl","c":{"a":0,"k":[1,1,1,1],"ix":4},"o":{"a":0,"k":100,"ix":5},"r":1,"bm":0,"nm":"Fill 1","mn":"ADBE Vector Graphic - Fill","hd":false},{"ty":"tr","p":{"a":0,"k":[0,0],"ix":2},"a":{"a":0,"k":[0,0],"ix":1},"s":{"a":0,"k":[100,100],"ix":3},"r":{"a":0,"k":0,"ix":6},"o":{"a":0,"k":100,"ix":7},"sk":{"a":0,"k":0,"ix":4},"sa":{"a":0,"k":0,"ix":5},"nm":"Transform"}],"nm":"Shape 2","np":3,"cix":2,"bm":0,"ix":1,"mn":"ADBE Vector Group","hd":false},{"ty":"gr","it":[{"ind":0,"ty":"sh","ix":1,"ks":{"a":0,"k":{"i":[[16.68,3.776],[0,0],[0,0],[-32.341,29.768]],"o":[[-34.164,-7.734],[0,0],[0,0],[12.583,-11.582]],"v":[[216.5,-294],[114.25,-269.75],[106.5,-192.75],[228,-244]],"c":true},"ix":2},"nm":"Path 1","mn":"ADBE Vector Shape - Group","hd":false},{"ty":"st","c":{"a":0,"k":[0.749019607843,0.407843167174,0.090196078431,1],"ix":3},"o":{"a":0,"k":100,"ix":4},"w":{"a":0,"k":0,"ix":5},"lc":1,"lj":1,"ml":4,"bm":0,"nm":"Stroke 1","mn":"ADBE Vector Graphic - Stroke","hd":false},{"ty":"fl","c":{"a":0,"k":[1,1,1,1],"ix":4},"o":{"a":0,"k":100,"ix":5},"r":1,"bm":0,"nm":"Fill 1","mn":"ADBE Vector Graphic - Fill","hd":false},{"ty":"tr","p":{"a":0,"k":[0,0],"ix":2},"a":{"a":0,"k":[0,0],"ix":1},"s":{"a":0,"k":[100,100],"ix":3},"r":{"a":0,"k":0,"ix":6},"o":{"a":0,"k":100,"ix":7},"sk":{"a":0,"k":0,"ix":4},"sa":{"a":0,"k":0,"ix":5},"nm":"Transform"}],"nm":"Shape 1","np":3,"cix":2,"bm":0,"ix":2,"mn":"ADBE Vector Group","hd":false}],"ip":0,"op":917.000037350176,"st":0,"bm":0},{"ddd":0,"ind":13,"ty":4,"nm":"orange line2","tt":2,"sr":1,"ks":{"o":{"a":0,"k":100,"ix":11},"r":{"a":0,"k":0,"ix":10},"p":{"a":0,"k":[375,667,0],"ix":2},"a":{"a":0,"k":[0,0,0],"ix":1},"s":{"a":0,"k":[100,100,100],"ix":6}},"ao":0,"shapes":[{"ty":"gr","it":[{"ind":0,"ty":"sh","ix":1,"ks":{"a":0,"k":{"i":[[0,0],[128.832,-186.026],[-34.439,-41.933],[-59.771,2.135],[-17.683,44.845],[40.829,35.462],[45.678,-35.83],[0,0],[-15.623,0.121],[-15.355,11.339]],"o":[[-115.723,99.324],[-30.894,44.609],[37.959,46.219],[48.175,-1.721],[19.837,-50.309],[-43.83,-38.069],[-48.217,37.822],[0,0],[14.044,-0.108],[0,0]],"v":[[427,-899],[-49,-415],[-19,-255],[144,-180],[261,-265],[241,-426],[67,-433.5],[23,-255],[92.391,-221.875],[152.5,-256]],"c":false},"ix":2},"nm":"Path 1","mn":"ADBE Vector Shape - Group","hd":false},{"ty":"st","c":{"a":0,"k":[0.749019607843,0.407843167174,0.090196078431,1],"ix":3},"o":{"a":0,"k":100,"ix":4},"w":{"a":0,"k":19,"ix":5},"lc":2,"lj":1,"ml":4,"bm":0,"nm":"Stroke 1","mn":"ADBE Vector Graphic - Stroke","hd":false},{"ty":"tr","p":{"a":0,"k":[0,0],"ix":2},"a":{"a":0,"k":[0,0],"ix":1},"s":{"a":0,"k":[100,100],"ix":3},"r":{"a":0,"k":0,"ix":6},"o":{"a":0,"k":100,"ix":7},"sk":{"a":0,"k":0,"ix":4},"sa":{"a":0,"k":0,"ix":5},"nm":"Transform"}],"nm":"Shape 1","np":3,"cix":2,"bm":0,"ix":1,"mn":"ADBE Vector Group","hd":false},{"ty":"tm","s":{"a":0,"k":0,"ix":1},"e":{"a":1,"k":[{"i":{"x":[0.833],"y":[1]},"o":{"x":[0.167],"y":[0]},"t":21,"s":[4]},{"t":66.0000026882351,"s":[16]}],"ix":2},"o":{"a":1,"k":[{"i":{"x":[0.833],"y":[1]},"o":{"x":[0.333],"y":[0]},"t":21,"s":[2]},{"t":66.0000026882351,"s":[354]}],"ix":3},"m":1,"ix":2,"nm":"Trim Paths 1","mn":"ADBE Vector Filter - Trim","hd":false}],"ip":0,"op":74.0000030140818,"st":0,"bm":0},{"ddd":0,"ind":14,"ty":4,"nm":"Shape Layer 1","td":1,"sr":1,"ks":{"o":{"a":0,"k":100,"ix":11},"r":{"a":0,"k":0,"ix":10},"p":{"a":0,"k":[379,879,0],"ix":2},"a":{"a":0,"k":[0,0,0],"ix":1},"s":{"a":0,"k":[100,100,100],"ix":6}},"ao":0,"shapes":[{"ty":"gr","it":[{"ind":0,"ty":"sh","ix":1,"ks":{"a":0,"k":{"i":[[0,0],[0,0],[0,0],[0,0],[0,0],[0,0]],"o":[[0,0],[0,0],[0,0],[0,0],[0,0],[0,0]],"v":[[80.615,-531.22],[82.871,-494.802],[51.045,-514.914],[232.644,-49.429],[315.212,-319.848],[96.69,-529.852]],"c":true},"ix":2},"nm":"Path 1","mn":"ADBE Vector Shape - Group","hd":false},{"ty":"st","c":{"a":0,"k":[0.749019607843,0.407843167174,0.090196078431,1],"ix":3},"o":{"a":0,"k":100,"ix":4},"w":{"a":0,"k":0,"ix":5},"lc":1,"lj":1,"ml":4,"bm":0,"nm":"Stroke 1","mn":"ADBE Vector Graphic - Stroke","hd":false},{"ty":"fl","c":{"a":0,"k":[0.835294117647,0.835294117647,0.835294117647,1],"ix":4},"o":{"a":0,"k":100,"ix":5},"r":1,"bm":0,"nm":"Fill 1","mn":"ADBE Vector Graphic - Fill","hd":false},{"ty":"tr","p":{"a":0,"k":[11.5,-4],"ix":2},"a":{"a":0,"k":[0,0],"ix":1},"s":{"a":0,"k":[100,100],"ix":3},"r":{"a":0,"k":-0.815,"ix":6},"o":{"a":0,"k":100,"ix":7},"sk":{"a":0,"k":0,"ix":4},"sa":{"a":0,"k":0,"ix":5},"nm":"Transform"}],"nm":"Shape 1","np":3,"cix":2,"bm":0,"ix":1,"mn":"ADBE Vector Group","hd":false}],"ip":32.0000013033867,"op":917.000037350176,"st":0,"bm":0},{"ddd":0,"ind":15,"ty":4,"nm":"orange line","tt":2,"sr":1,"ks":{"o":{"a":0,"k":100,"ix":11},"r":{"a":0,"k":0,"ix":10},"p":{"a":0,"k":[379,879,0],"ix":2},"a":{"a":0,"k":[0,0,0],"ix":1},"s":{"a":0,"k":[100,100,100],"ix":6}},"ao":0,"shapes":[{"ty":"gr","it":[{"ind":0,"ty":"sh","ix":1,"ks":{"a":0,"k":{"i":[[0,0],[-4.619,-73.904],[66,-97],[75.148,30.955],[-32.5,175.5],[-40.001,24.616],[-45.175,0.43],[-24.987,-23.364],[-0.684,0]],"o":[[-40,252],[6,96],[-45.72,67.195],[-84.012,-34.606],[14.016,-75.684],[26,-16],[52.5,-0.5],[53.979,50.473],[0,0]],"v":[[337,-1139],[279,-507],[213,-200],[-71,-109],[-224.5,-388.5],[-111.5,-520],[-5,-555],[89.409,-508.437],[273.5,-250.5]],"c":false},"ix":2},"nm":"Path 1","mn":"ADBE Vector Shape - Group","hd":false},{"ty":"st","c":{"a":0,"k":[0.749019607843,0.407843167174,0.090196078431,1],"ix":3},"o":{"a":0,"k":100,"ix":4},"w":{"a":0,"k":17.5,"ix":5},"lc":2,"lj":1,"ml":4,"bm":0,"nm":"Stroke 1","mn":"ADBE Vector Graphic - Stroke","hd":false},{"ty":"tr","p":{"a":0,"k":[0,0],"ix":2},"a":{"a":0,"k":[0,0],"ix":1},"s":{"a":0,"k":[100,100],"ix":3},"r":{"a":0,"k":0,"ix":6},"o":{"a":0,"k":100,"ix":7},"sk":{"a":0,"k":0,"ix":4},"sa":{"a":0,"k":0,"ix":5},"nm":"Transform"}],"nm":"Shape 1","np":3,"cix":2,"bm":0,"ix":1,"mn":"ADBE Vector Group","hd":false},{"ty":"tm","s":{"a":0,"k":0,"ix":1},"e":{"a":0,"k":9,"ix":2},"o":{"a":1,"k":[{"i":{"x":[0.833],"y":[1]},"o":{"x":[0.333],"y":[0]},"t":0,"s":[0]},{"t":69.0000028104276,"s":[360]}],"ix":3},"m":1,"ix":2,"nm":"Trim Paths 1","mn":"ADBE Vector Filter - Trim","hd":false}],"ip":0,"op":75.0000030548126,"st":0,"bm":0},{"ddd":0,"ind":16,"ty":4,"nm":"orange6","sr":1,"ks":{"o":{"a":1,"k":[{"i":{"x":[0.833],"y":[1]},"o":{"x":[0.333],"y":[0]},"t":52,"s":[0]},{"t":55.0000022401959,"s":[100]}],"ix":11},"r":{"a":0,"k":0,"ix":10},"p":{"a":0,"k":[415.585,345.619,0],"ix":2},"a":{"a":0,"k":[99.858,21.752,0],"ix":1},"s":{"a":0,"k":[151.293,151.293,100],"ix":6}},"ao":0,"shapes":[{"ty":"gr","it":[{"ind":0,"ty":"sh","ix":1,"ks":{"a":0,"k":{"i":[[-0.081,-0.699],[0.612,0.348],[1.558,0.893],[1.527,0.907],[0.204,0.256],[0.776,0.814],[2.17,1.99],[1.704,1.156],[2.111,1.208],[1.558,0.664],[1.776,0.571],[1.946,0.414],[2.161,0.313],[1.205,0.073],[1.062,0.056],[0.066,0.114],[1.62,2.823],[0.579,1.026],[0.059,0.2],[-1.592,0.038],[-1.803,-0.066],[-1.535,-0.163],[-1.518,-0.243],[-3.166,-1.023],[-1.579,-0.635],[-1.962,-0.95],[-1.625,-0.97],[-1.48,-1.031],[-1.161,-0.957],[-1.571,-1.447],[-1.09,-1.183],[-0.981,-1.215],[-0.425,-0.892],[-0.059,-0.599],[-0.178,-1.926],[-0.124,-1.409]],"o":[[-0.697,-0.383],[-1.56,-0.89],[-1.542,-0.883],[-0.267,-0.159],[-0.705,-0.881],[-2.034,-2.134],[-1.513,-1.387],[-2.012,-1.366],[-1.467,-0.84],[-1.717,-0.732],[-1.894,-0.609],[-2.134,-0.454],[-1.193,-0.173],[-1.061,-0.065],[-0.132,-0.007],[-1.632,-2.816],[-0.587,-1.022],[-0.051,-0.091],[1.645,-0.091],[1.804,-0.043],[1.541,0.056],[1.529,0.162],[3.286,0.526],[1.619,0.523],[2.023,0.813],[1.701,0.824],[1.549,0.925],[1.234,0.859],[1.649,1.359],[1.182,1.089],[1.06,1.149],[0.623,0.772],[0.244,0.511],[0.189,1.925],[0.13,1.408],[0.049,0.556]],"v":[[133.503,43.442],[131.574,42.379],[126.9,39.698],[122.28,37.04],[121.629,36.311],[119.512,33.669],[113.29,27.387],[108.366,23.653],[102.177,19.783],[97.592,17.586],[92.361,15.579],[86.588,14.039],[80.129,12.949],[76.519,12.649],[73.331,12.519],[72.955,12.288],[68.083,3.827],[66.334,0.756],[66.212,0.352],[71.04,0.095],[76.456,0.109],[81.072,0.484],[85.647,1.076],[95.327,3.414],[100.137,5.132],[106.139,7.735],[111.109,10.481],[115.656,13.419],[119.237,16.171],[124.104,20.341],[127.454,23.817],[130.552,27.338],[132.167,29.848],[132.377,31.629],[132.942,37.405],[133.297,41.633]],"c":true},"ix":2},"nm":"Path 1","mn":"ADBE Vector Shape - Group","hd":false},{"ty":"st","c":{"a":0,"k":[1,1,1,1],"ix":3},"o":{"a":0,"k":100,"ix":4},"w":{"a":0,"k":0,"ix":5},"lc":1,"lj":1,"ml":4,"bm":0,"nm":"Stroke 1","mn":"ADBE Vector Graphic - Stroke","hd":false},{"ty":"fl","c":{"a":1,"k":[{"i":{"x":[0.667],"y":[1]},"o":{"x":[0.333],"y":[0]},"t":74,"s":[0.749019622803,0.40784317255,0.090196080506,1]},{"t":88.0000035843135,"s":[0.011764707044,0.454901993275,0.211764723063,1]}],"ix":4},"o":{"a":0,"k":100,"ix":5},"r":1,"bm":0,"nm":"Fill 1","mn":"ADBE Vector Graphic - Fill","hd":false},{"ty":"tr","p":{"a":0,"k":[0,0],"ix":2},"a":{"a":0,"k":[0,0],"ix":1},"s":{"a":0,"k":[100,100],"ix":3},"r":{"a":0,"k":0,"ix":6},"o":{"a":0,"k":100,"ix":7},"sk":{"a":0,"k":0,"ix":4},"sa":{"a":0,"k":0,"ix":5},"nm":"Transform"}],"nm":"Shape 1","np":3,"cix":2,"bm":0,"ix":1,"mn":"ADBE Vector Group","hd":false}],"ip":0,"op":694.0000282672,"st":0,"bm":0},{"ddd":0,"ind":17,"ty":4,"nm":"orange5","sr":1,"ks":{"o":{"a":1,"k":[{"i":{"x":[0.667],"y":[1]},"o":{"x":[0.167],"y":[0]},"t":58,"s":[1]},{"t":59.0000024031193,"s":[100]}],"ix":11},"r":{"a":0,"k":0,"ix":10},"p":{"a":0,"k":[452.572,389.056,0],"ix":2},"a":{"a":0,"k":[124.503,49.337,0],"ix":1},"s":{"a":0,"k":[151.293,151.293,100],"ix":6}},"ao":0,"shapes":[{"ty":"gr","it":[{"ind":0,"ty":"sh","ix":1,"ks":{"a":0,"k":{"i":[[-0.069,0.217],[-0.72,-0.577],[-1.414,-1.294],[-1.242,-1.287],[-0.297,-0.438],[-0.002,-0.295],[0.009,-3.228],[-0.338,-0.206],[-2.65,-1.618],[-0.915,-0.338],[-2.399,1.781],[-0.698,1.105],[-1.388,2.214],[-0.258,-0.661],[-0.732,-3.281],[-0.405,-1.766],[0.447,-0.636],[2.58,-1.07],[1.207,-0.173],[1.224,0.092],[1.995,0.734],[2.004,1.155],[2.157,1.313],[2.348,1.43],[0.688,0.379],[0.003,0.356],[0.015,3.221],[0.017,4.107],[-0.499,1.909]],"o":[[0.755,0.531],[1.497,1.2],[1.317,1.206],[0.37,0.383],[0.162,0.238],[0.016,3.228],[-0.001,0.346],[2.65,1.618],[0.839,0.513],[2.635,0.973],[1.059,-0.786],[1.331,-2.107],[0.274,0.715],[1.227,3.135],[0.395,1.769],[0.231,1.007],[-1.595,2.275],[-1.123,0.466],[-1.215,0.174],[-2.114,-0.159],[-2.204,-0.811],[-2.188,-1.26],[-2.348,-1.429],[-0.671,-0.408],[-0.301,-0.166],[-0.025,-3.221],[-0.019,-4.107],[-0.009,-1.995],[0.042,-0.162]],"v":[[104.255,27.665],[106.516,29.267],[110.939,32.951],[114.701,36.775],[115.738,37.99],[115.977,38.865],[115.982,48.55],[116.377,49.333],[124.302,54.229],[126.909,55.614],[134.554,54.936],[137.075,51.98],[141.112,45.543],[141.895,47.583],[144.795,57.223],[145.81,62.566],[144.923,64.764],[138.711,69.916],[135.154,70.841],[131.458,70.961],[125.312,69.513],[119.25,66.13],[112.769,62.207],[105.727,57.915],[103.702,56.709],[103.261,56.004],[103.159,46.341],[103.149,34.019],[104.086,28.201]],"c":true},"ix":2},"nm":"Path 1","mn":"ADBE Vector Shape - Group","hd":false},{"ty":"st","c":{"a":0,"k":[1,1,1,1],"ix":3},"o":{"a":0,"k":100,"ix":4},"w":{"a":0,"k":0,"ix":5},"lc":1,"lj":1,"ml":4,"bm":0,"nm":"Stroke 1","mn":"ADBE Vector Graphic - Stroke","hd":false},{"ty":"fl","c":{"a":1,"k":[{"i":{"x":[0.667],"y":[1]},"o":{"x":[0.333],"y":[0]},"t":79,"s":[1,0.713725490196,0.254901960784,1]},{"t":88.0000035843135,"s":[0.643137276173,0.811764776707,0.215686291456,1]}],"ix":4},"o":{"a":0,"k":100,"ix":5},"r":1,"bm":0,"nm":"Fill 1","mn":"ADBE Vector Graphic - Fill","hd":false},{"ty":"tr","p":{"a":0,"k":[0,0],"ix":2},"a":{"a":0,"k":[0,0],"ix":1},"s":{"a":0,"k":[100,100],"ix":3},"r":{"a":0,"k":0,"ix":6},"o":{"a":0,"k":100,"ix":7},"sk":{"a":0,"k":0,"ix":4},"sa":{"a":0,"k":0,"ix":5},"nm":"Transform"}],"nm":"Shape 1","np":3,"cix":2,"bm":0,"ix":1,"mn":"ADBE Vector Group","hd":false}],"ip":0,"op":2756.241112264,"st":0,"bm":0},{"ddd":0,"ind":18,"ty":4,"nm":"orange4","sr":1,"ks":{"o":{"a":1,"k":[{"i":{"x":[0.667],"y":[1]},"o":{"x":[0.167],"y":[0]},"t":57,"s":[0]},{"t":59.0000024031193,"s":[100]}],"ix":11},"r":{"a":0,"k":0,"ix":10},"p":{"a":0,"k":[437.682,398.144,0],"ix":2},"a":{"a":0,"k":[114.349,56.664,0],"ix":1},"s":{"a":0,"k":[151.293,151.293,100],"ix":6}},"ao":0,"shapes":[{"ty":"gr","it":[{"ind":0,"ty":"sh","ix":1,"ks":{"a":0,"k":{"i":[[-0.055,-0.016],[0.077,-0.917],[0.199,-1.587],[0.324,-1.788],[0.323,-1.285],[0.129,-0.088],[1.285,-0.208],[1.557,-0.089],[3.574,1.024],[2.059,1.118],[1.829,1.098],[2.404,1.446],[2.965,1.783],[2.502,1.501],[2.105,1.324],[0.002,0.36],[0,3.591],[0.01,1.872],[0.048,6.354],[-0.073,1.381],[-0.231,1.541],[-0.225,1.193],[-0.492,-0.123],[-1.601,-0.47],[-1.438,-0.528],[-1.021,-0.451],[0.028,-0.124],[0.353,-1.641],[0.001,-0.767],[0.018,-9.857],[-0.367,-0.219],[-4.808,-2.891],[-3.881,-2.216],[-1.554,-0.45],[-1.662,-0.189],[-1.513,0.023],[-1.46,0.499],[-1.703,1.401],[-0.211,0.16]],"o":[[-0.051,0.919],[-0.134,1.595],[-0.226,1.803],[-0.237,1.302],[-0.034,0.136],[-1.112,0.768],[-1.539,0.249],[-3.731,0.214],[-2.249,-0.644],[-1.872,-1.017],[-2.405,-1.445],[-2.965,-1.783],[-2.5,-1.504],[-2.133,-1.279],[-0.241,-0.151],[-0.024,-3.591],[0,-1.872],[-0.034,-6.354],[-0.01,-1.387],[0.082,-1.553],[0.18,-1.199],[0.09,-0.476],[1.619,0.406],[1.469,0.431],[1.047,0.385],[0.122,0.054],[-0.374,1.636],[-0.161,0.75],[-0.016,9.857],[-0.001,0.471],[4.817,2.876],[3.831,2.304],[1.392,0.795],[1.61,0.466],[1.494,0.17],[1.551,-0.024],[2.103,-0.719],[0.204,-0.168],[0.055,0.016]],"v":[[146.63,75.158],[146.471,77.915],[146.014,82.695],[145.2,88.086],[144.286,91.953],[143.969,92.304],[140.268,93.541],[135.609,94.012],[124.675,92.576],[118.136,90.1],[112.638,86.829],[105.426,82.49],[96.53,77.143],[89.03,72.63],[82.641,68.775],[82.308,67.727],[82.293,56.953],[82.292,51.337],[82.175,32.275],[82.088,28.115],[82.626,23.472],[83.325,19.897],[84.139,19.307],[88.99,20.552],[93.341,22.03],[96.431,23.319],[96.664,23.751],[95.505,28.651],[95.252,30.949],[95.227,60.52],[95.763,61.464],[110.208,70.101],[121.699,77.016],[126.239,78.752],[131.17,79.774],[135.706,79.81],[140.202,78.901],[145.834,75.59],[146.465,75.11]],"c":true},"ix":2},"nm":"Path 1","mn":"ADBE Vector Shape - Group","hd":false},{"ty":"st","c":{"a":0,"k":[1,1,1,1],"ix":3},"o":{"a":0,"k":100,"ix":4},"w":{"a":0,"k":0,"ix":5},"lc":1,"lj":1,"ml":4,"bm":0,"nm":"Stroke 1","mn":"ADBE Vector Graphic - Stroke","hd":false},{"ty":"fl","c":{"a":1,"k":[{"i":{"x":[0.667],"y":[1]},"o":{"x":[0.333],"y":[0]},"t":84,"s":[0.749019607843,0.407843167174,0.090196078431,1]},{"t":93.0000037879676,"s":[0.007843137719,0.450980424881,0.207843154669,1]}],"ix":4},"o":{"a":0,"k":100,"ix":5},"r":1,"bm":0,"nm":"Fill 1","mn":"ADBE Vector Graphic - Fill","hd":false},{"ty":"tr","p":{"a":0,"k":[0,0],"ix":2},"a":{"a":0,"k":[0,0],"ix":1},"s":{"a":0,"k":[100,100],"ix":3},"r":{"a":0,"k":0,"ix":6},"o":{"a":0,"k":100,"ix":7},"sk":{"a":0,"k":0,"ix":4},"sa":{"a":0,"k":0,"ix":5},"nm":"Transform"}],"nm":"Shape 1","np":3,"cix":2,"bm":0,"ix":1,"mn":"ADBE Vector Group","hd":false}],"ip":0,"op":2756.241112264,"st":0,"bm":0},{"ddd":0,"ind":19,"ty":4,"nm":"Shape Layer 5","td":1,"sr":1,"ks":{"o":{"a":0,"k":100,"ix":11},"r":{"a":0,"k":0,"ix":10},"p":{"a":0,"k":[375,667,0],"ix":2},"a":{"a":0,"k":[0,0,0],"ix":1},"s":{"a":0,"k":[100,100,100],"ix":6}},"ao":0,"shapes":[{"ty":"gr","it":[{"ind":0,"ty":"sh","ix":1,"ks":{"a":0,"k":{"i":[[0,0],[0,0],[0,0],[-11.912,7.924],[-6.053,6.268],[-0.361,8.596]],"o":[[0,0],[0,0],[0,0],[7.255,-4.826],[5.977,-6.189],[0.547,-13.015]],"v":[[100,-222.5],[36.25,-163.5],[40,-124.75],[75.75,-148.5],[97.5,-163],[111,-185]],"c":true},"ix":2},"nm":"Path 1","mn":"ADBE Vector Shape - Group","hd":false},{"ty":"st","c":{"a":0,"k":[0.007843137255,0.450980422076,0.207843152214,1],"ix":3},"o":{"a":0,"k":100,"ix":4},"w":{"a":0,"k":0,"ix":5},"lc":1,"lj":1,"ml":4,"bm":0,"nm":"Stroke 1","mn":"ADBE Vector Graphic - Stroke","hd":false},{"ty":"fl","c":{"a":0,"k":[1,1,1,1],"ix":4},"o":{"a":0,"k":100,"ix":5},"r":1,"bm":0,"nm":"Fill 1","mn":"ADBE Vector Graphic - Fill","hd":false},{"ty":"tr","p":{"a":0,"k":[0,0],"ix":2},"a":{"a":0,"k":[0,0],"ix":1},"s":{"a":0,"k":[100,100],"ix":3},"r":{"a":0,"k":0,"ix":6},"o":{"a":0,"k":100,"ix":7},"sk":{"a":0,"k":0,"ix":4},"sa":{"a":0,"k":0,"ix":5},"nm":"Transform"}],"nm":"Shape 1","np":3,"cix":2,"bm":0,"ix":1,"mn":"ADBE Vector Group","hd":false}],"ip":0,"op":917.000037350176,"st":0,"bm":0},{"ddd":0,"ind":20,"ty":4,"nm":"green line3","tt":2,"sr":1,"ks":{"o":{"a":0,"k":100,"ix":11},"r":{"a":0,"k":0,"ix":10},"p":{"a":0,"k":[375,667,0],"ix":2},"a":{"a":0,"k":[0,0,0],"ix":1},"s":{"a":0,"k":[100,100,100],"ix":6}},"ao":0,"shapes":[{"ty":"gr","it":[{"ind":0,"ty":"sh","ix":1,"ks":{"a":0,"k":{"i":[[0,0],[-366.01,-150.614],[-30.517,84.273],[52.823,62.113],[0,0],[0,0],[-6.468,-10.852],[0,0],[-19.201,60.031]],"o":[[208.261,167.909],[82.885,34.107],[27.762,-76.666],[-47.504,-55.858],[0,0],[0,0],[23.371,39.213],[0,0],[0,0]],"v":[[-978.056,-381.877],[12.738,272.464],[231.231,115.748],[153.471,-116.176],[-45.604,-209.773],[-91.061,-170.163],[-95.169,-132.486],[-6.436,-28.174],[51.167,-208.266]],"c":false},"ix":2},"nm":"Path 1","mn":"ADBE Vector Shape - Group","hd":false},{"ty":"st","c":{"a":0,"k":[0.007843137255,0.450980422076,0.207843152214,1],"ix":3},"o":{"a":0,"k":100,"ix":4},"w":{"a":0,"k":17.5,"ix":5},"lc":2,"lj":1,"ml":4,"bm":0,"nm":"Stroke 1","mn":"ADBE Vector Graphic - Stroke","hd":false},{"ty":"tr","p":{"a":0,"k":[0,0],"ix":2},"a":{"a":0,"k":[0,0],"ix":1},"s":{"a":0,"k":[100,100],"ix":3},"r":{"a":0,"k":11.71,"ix":6},"o":{"a":0,"k":100,"ix":7},"sk":{"a":0,"k":0,"ix":4},"sa":{"a":0,"k":0,"ix":5},"nm":"Transform"}],"nm":"Shape 1","np":3,"cix":2,"bm":0,"ix":1,"mn":"ADBE Vector Group","hd":false},{"ty":"tm","s":{"a":0,"k":0,"ix":1},"e":{"a":1,"k":[{"i":{"x":[0.667],"y":[1]},"o":{"x":[0.167],"y":[0]},"t":30,"s":[10]},{"t":62.0000025253118,"s":[29]}],"ix":2},"o":{"a":1,"k":[{"i":{"x":[0.833],"y":[1]},"o":{"x":[0.333],"y":[0]},"t":23,"s":[0]},{"t":69.0000028104276,"s":[362]}],"ix":3},"m":1,"ix":2,"nm":"Trim Paths 1","mn":"ADBE Vector Filter - Trim","hd":false}],"ip":3.00000012219251,"op":925.000037676022,"st":3.00000012219251,"bm":0},{"ddd":0,"ind":21,"ty":4,"nm":"Shape Layer 4","td":1,"sr":1,"ks":{"o":{"a":0,"k":100,"ix":11},"r":{"a":0,"k":0,"ix":10},"p":{"a":0,"k":[375,667,0],"ix":2},"a":{"a":0,"k":[0,0,0],"ix":1},"s":{"a":0,"k":[100,100,100],"ix":6}},"ao":0,"shapes":[{"ty":"gr","it":[{"ind":0,"ty":"sh","ix":1,"ks":{"a":0,"k":{"i":[[0,0],[0,0],[0,0],[0,0],[0,0],[0,0]],"o":[[0,0],[0,0],[0,0],[0,0],[0,0],[0,0]],"v":[[52,-172.25],[5.125,-157.125],[1,-120.75],[51.5,-127.125],[42.618,-138.493],[68.584,-153.846]],"c":true},"ix":2},"nm":"Path 1","mn":"ADBE Vector Shape - Group","hd":false},{"ty":"st","c":{"a":0,"k":[0.647058823529,0.815686334348,0.219607858097,1],"ix":3},"o":{"a":0,"k":100,"ix":4},"w":{"a":0,"k":0,"ix":5},"lc":1,"lj":1,"ml":4,"bm":0,"nm":"Stroke 1","mn":"ADBE Vector Graphic - Stroke","hd":false},{"ty":"fl","c":{"a":0,"k":[1,1,1,1],"ix":4},"o":{"a":0,"k":100,"ix":5},"r":1,"bm":0,"nm":"Fill 1","mn":"ADBE Vector Graphic - Fill","hd":false},{"ty":"tr","p":{"a":0,"k":[0,0],"ix":2},"a":{"a":0,"k":[0,0],"ix":1},"s":{"a":0,"k":[100,100],"ix":3},"r":{"a":0,"k":0,"ix":6},"o":{"a":0,"k":100,"ix":7},"sk":{"a":0,"k":0,"ix":4},"sa":{"a":0,"k":0,"ix":5},"nm":"Transform"}],"nm":"Shape 1","np":3,"cix":2,"bm":0,"ix":1,"mn":"ADBE Vector Group","hd":false}],"ip":0,"op":917.000037350176,"st":0,"bm":0},{"ddd":0,"ind":22,"ty":4,"nm":"green line2","tt":2,"sr":1,"ks":{"o":{"a":0,"k":100,"ix":11},"r":{"a":0,"k":0,"ix":10},"p":{"a":0,"k":[375,667,0],"ix":2},"a":{"a":0,"k":[0,0,0],"ix":1},"s":{"a":0,"k":[100,100,100],"ix":6}},"ao":0,"shapes":[{"ty":"gr","it":[{"ind":0,"ty":"sh","ix":1,"ks":{"a":0,"k":{"i":[[0,0],[-224.518,-85.557],[-41.153,62.764],[35.524,58.762],[0,0],[0,0],[-1.702,-7.332],[0,0],[-9.75,18.583]],"o":[[128.494,99.481],[70.133,26.725],[37.651,-57.422],[-31.837,-52.663],[0,0],[0,0],[5.638,24.286],[0,0],[0,0]],"v":[[-637,-185],[-27,199],[187,129],[152,-74],[0.5,-179.5],[-20.25,-168.5],[-34.698,-151.147],[-0.75,-84.5],[28.5,-140.25]],"c":false},"ix":2},"nm":"Path 1","mn":"ADBE Vector Shape - Group","hd":false},{"ty":"st","c":{"a":0,"k":[0.647058823529,0.815686334348,0.219607858097,1],"ix":3},"o":{"a":0,"k":100,"ix":4},"w":{"a":0,"k":17.5,"ix":5},"lc":2,"lj":1,"ml":4,"bm":0,"nm":"Stroke 1","mn":"ADBE Vector Graphic - Stroke","hd":false},{"ty":"tr","p":{"a":0,"k":[0,0],"ix":2},"a":{"a":0,"k":[0,0],"ix":1},"s":{"a":0,"k":[100,100],"ix":3},"r":{"a":0,"k":0,"ix":6},"o":{"a":0,"k":100,"ix":7},"sk":{"a":0,"k":0,"ix":4},"sa":{"a":0,"k":0,"ix":5},"nm":"Transform"}],"nm":"Shape 1","np":3,"cix":2,"bm":0,"ix":1,"mn":"ADBE Vector Group","hd":false},{"ty":"tm","s":{"a":0,"k":0,"ix":1},"e":{"a":0,"k":17,"ix":2},"o":{"a":1,"k":[{"i":{"x":[0.833],"y":[1]},"o":{"x":[0.333],"y":[0]},"t":22,"s":[0]},{"t":68.0000027696968,"s":[362]}],"ix":3},"m":1,"ix":2,"nm":"Trim Paths 1","mn":"ADBE Vector Filter - Trim","hd":false}],"ip":0,"op":922.00003755383,"st":0,"bm":0},{"ddd":0,"ind":23,"ty":4,"nm":"Shape Layer 2","td":1,"sr":1,"ks":{"o":{"a":0,"k":100,"ix":11},"r":{"a":0,"k":0,"ix":10},"p":{"a":0,"k":[379,879,0],"ix":2},"a":{"a":0,"k":[0,0,0],"ix":1},"s":{"a":0,"k":[100,100,100],"ix":6}},"ao":0,"shapes":[{"ty":"gr","it":[{"ind":0,"ty":"sh","ix":1,"ks":{"a":0,"k":{"i":[[0,0],[0,0],[0,0],[0,0],[0,0]],"o":[[0,0],[0,0],[0,0],[0,0],[0,0]],"v":[[58.75,-363],[-134,-372],[-150.75,-298.5],[56.5,-308.25],[7.437,-331.201]],"c":true},"ix":2},"nm":"Path 1","mn":"ADBE Vector Shape - Group","hd":false},{"ty":"st","c":{"a":0,"k":[0.007843137255,0.450980422076,0.207843152214,1],"ix":3},"o":{"a":0,"k":100,"ix":4},"w":{"a":0,"k":0,"ix":5},"lc":1,"lj":1,"ml":4,"bm":0,"nm":"Stroke 1","mn":"ADBE Vector Graphic - Stroke","hd":false},{"ty":"fl","c":{"a":0,"k":[0.835294117647,0.835294117647,0.835294117647,1],"ix":4},"o":{"a":0,"k":100,"ix":5},"r":1,"bm":0,"nm":"Fill 1","mn":"ADBE Vector Graphic - Fill","hd":false},{"ty":"tr","p":{"a":0,"k":[-15.75,-22.25],"ix":2},"a":{"a":0,"k":[0,0],"ix":1},"s":{"a":0,"k":[100,100],"ix":3},"r":{"a":0,"k":0,"ix":6},"o":{"a":0,"k":100,"ix":7},"sk":{"a":0,"k":0,"ix":4},"sa":{"a":0,"k":0,"ix":5},"nm":"Transform"}],"nm":"Shape 1","np":3,"cix":2,"bm":0,"ix":1,"mn":"ADBE Vector Group","hd":false}],"ip":0,"op":917.000037350176,"st":0,"bm":0},{"ddd":0,"ind":24,"ty":4,"nm":"green line","tt":2,"sr":1,"ks":{"o":{"a":0,"k":100,"ix":11},"r":{"a":0,"k":69,"ix":10},"p":{"a":0,"k":[399.192,541.234,0],"ix":2},"a":{"a":0,"k":[32.192,-459.766,0],"ix":1},"s":{"a":0,"k":[100,100,100],"ix":6}},"ao":0,"shapes":[{"ty":"gr","it":[{"ind":0,"ty":"sh","ix":1,"ks":{"a":0,"k":{"i":[[0,0],[39.556,-173.699],[96.209,-34.753],[72.776,41.308],[17.353,63.012],[-23.775,52.236],[-32.587,12.63],[-20.54,-10.358],[-23.781,-23.617],[-5.219,-21.031],[6.753,-24.744],[11.922,-20.681]],"o":[[27.51,119.67],[-22.713,99.74],[-78.704,28.43],[-56.84,-32.263],[-15.238,-55.332],[14.478,-31.809],[21.449,-8.313],[29.925,15.092],[15.375,15.269],[6.177,24.894],[-9.325,34.168],[0,0]],"v":[[256.189,-942.641],[299.163,-409.933],[84.858,-190.277],[-160.388,-243.929],[-281.431,-398.182],[-249.459,-567.363],[-172.18,-638.221],[-104.77,-623.439],[-24.037,-563.51],[10.824,-508.642],[8.665,-431.726],[-36.424,-335.515]],"c":false},"ix":2},"nm":"Path 1","mn":"ADBE Vector Shape - Group","hd":false},{"ty":"st","c":{"a":0,"k":[0.007843137255,0.450980422076,0.207843152214,1],"ix":3},"o":{"a":0,"k":100,"ix":4},"w":{"a":0,"k":19,"ix":5},"lc":2,"lj":1,"ml":4,"bm":0,"nm":"Stroke 1","mn":"ADBE Vector Graphic - Stroke","hd":false},{"ty":"tr","p":{"a":0,"k":[0,0],"ix":2},"a":{"a":0,"k":[0,0],"ix":1},"s":{"a":0,"k":[100,100],"ix":3},"r":{"a":0,"k":0,"ix":6},"o":{"a":0,"k":100,"ix":7},"sk":{"a":0,"k":0,"ix":4},"sa":{"a":0,"k":0,"ix":5},"nm":"Transform"}],"nm":"Shape 1","np":3,"cix":2,"bm":0,"ix":1,"mn":"ADBE Vector Group","hd":false},{"ty":"tm","s":{"a":0,"k":0,"ix":1},"e":{"a":0,"k":8,"ix":2},"o":{"a":1,"k":[{"i":{"x":[0.833],"y":[1]},"o":{"x":[0.167],"y":[0]},"t":7,"s":[364]},{"t":68.0000027696968,"s":[723]}],"ix":3},"m":1,"ix":2,"nm":"Trim Paths 1","mn":"ADBE Vector Filter - Trim","hd":false}],"ip":0,"op":922.00003755383,"st":0,"bm":0},{"ddd":0,"ind":25,"ty":4,"nm":"green6","sr":1,"ks":{"o":{"a":1,"k":[{"i":{"x":[0.833],"y":[1]},"o":{"x":[0.333],"y":[0]},"t":54,"s":[0]},{"t":57.0000023216576,"s":[100]}],"ix":11},"r":{"a":0,"k":0,"ix":10},"p":{"a":0,"k":[423.11,502.476,0],"ix":2},"a":{"a":0,"k":[104.835,124.954,0],"ix":1},"s":{"a":0,"k":[151.293,151.293,100],"ix":6}},"ao":0,"shapes":[{"ty":"gr","it":[{"ind":0,"ty":"sh","ix":1,"ks":{"a":0,"k":{"i":[[1.002,0.457],[-0.982,0.574],[-1.713,0.997],[-0.956,0.511],[-0.348,0.06],[-1.757,0.436],[-2.389,0.787],[-1.517,0.676],[-2.987,2.149],[-1.425,1.215],[-1.456,1.488],[-1.182,1.396],[-1.514,2.614],[-0.421,-0.002],[-4.355,0.001],[-0.172,-0.024],[0.795,-1.369],[1.527,-2.283],[1.316,-1.707],[2.434,-2.228],[2.367,-1.793],[3.257,-1.577],[2.699,-1.093],[3.207,-0.714],[2.006,-0.447],[0.932,0.399],[2.775,1.265]],"o":[[1.113,-0.66],[1.712,-0.999],[0.937,-0.547],[0.297,-0.158],[1.788,-0.309],[2.441,-0.606],[1.574,-0.519],[3.363,-1.496],[1.521,-1.094],[1.586,-1.352],[1.278,-1.305],[1.955,-2.309],[0.197,-0.339],[4.355,0.017],[0.069,0],[-0.729,1.476],[-1.38,2.377],[-1.197,1.788],[-2.025,2.626],[-2.189,2.002],[-2.883,2.183],[-2.62,1.27],[-3.047,1.234],[-2.006,0.447],[-1.177,0.262],[-2.803,-1.2],[-0.863,-0.394]],"v":[[69.427,140.451],[72.498,138.63],[77.639,135.643],[80.452,134.007],[81.485,133.801],[86.844,132.852],[94.092,130.741],[98.705,128.858],[108.236,123.387],[112.683,119.944],[117.271,115.693],[120.871,111.552],[126.013,104.123],[126.868,103.643],[139.932,103.648],[140.242,103.691],[138.09,108.004],[133.764,115.024],[129.877,120.19],[123.083,127.397],[116.188,133.042],[106.964,138.699],[98.982,142.255],[89.56,145.1],[83.489,146.201],[80.49,145.467],[72.157,141.694]],"c":true},"ix":2},"nm":"Path 1","mn":"ADBE Vector Shape - Group","hd":false},{"ty":"st","c":{"a":0,"k":[1,1,1,1],"ix":3},"o":{"a":0,"k":100,"ix":4},"w":{"a":0,"k":0,"ix":5},"lc":1,"lj":1,"ml":4,"bm":0,"nm":"Stroke 1","mn":"ADBE Vector Graphic - Stroke","hd":false},{"ty":"fl","c":{"a":0,"k":[0.007843137255,0.450980422076,0.207843152214,1],"ix":4},"o":{"a":0,"k":100,"ix":5},"r":1,"bm":0,"nm":"Fill 1","mn":"ADBE Vector Graphic - Fill","hd":false},{"ty":"tr","p":{"a":0,"k":[0,0],"ix":2},"a":{"a":0,"k":[0,0],"ix":1},"s":{"a":0,"k":[100,100],"ix":3},"r":{"a":0,"k":0,"ix":6},"o":{"a":0,"k":100,"ix":7},"sk":{"a":0,"k":0,"ix":4},"sa":{"a":0,"k":0,"ix":5},"nm":"Transform"}],"nm":"Shape 1","np":3,"cix":2,"bm":0,"ix":1,"mn":"ADBE Vector Group","hd":false}],"ip":0,"op":706.00002875597,"st":0,"bm":0},{"ddd":0,"ind":26,"ty":4,"nm":"green5","sr":1,"ks":{"o":{"a":1,"k":[{"i":{"x":[0.833],"y":[1]},"o":{"x":[0.333],"y":[0]},"t":57,"s":[0]},{"t":59.0000024031193,"s":[100]}],"ix":11},"r":{"a":0,"k":0,"ix":10},"p":{"a":0,"k":[370.545,537.658,0],"ix":2},"a":{"a":0,"k":[70.764,148.315,0],"ix":1},"s":{"a":0,"k":[151.293,151.293,100],"ix":6}},"ao":0,"shapes":[{"ty":"gr","it":[{"ind":0,"ty":"sh","ix":1,"ks":{"a":0,"k":{"i":[[-1.004,-1.657],[-0.663,1.144],[-0.868,1.463],[-0.198,0.021],[-1.927,0.212],[-3.619,1.024],[-0.205,-0.058],[7.441,-12.789],[0.356,0.584],[1.8,2.998],[1.731,2.931],[1.613,2.783],[1.151,2.1],[1.777,3.277],[0.783,2.529],[0.124,0.981],[-2.196,3.018],[-1.872,1.299],[-1.127,0.628],[-2.693,1.476],[-1.709,0.932],[-1.535,0.861],[-0.273,-0.159],[-2.45,-1.405],[-1.909,-1.108],[-2.429,-1.477],[-0.578,-0.509],[-0.606,-0.567],[4.108,-1.016],[0.92,-0.159],[0.147,0.082],[1.443,0.831],[1.546,0.876],[0.11,-0.059],[2.076,-1.123],[1.21,-0.838],[0.471,-2.48],[-0.713,-1.431],[-1.12,-1.949],[-2.483,-4.212]],"o":[[0.729,-1.24],[0.853,-1.473],[0.092,-0.156],[1.928,-0.207],[3.744,-0.412],[0.03,-0.008],[-7.388,12.699],[-0.472,-0.752],[-1.821,-2.986],[-1.752,-2.919],[-1.636,-2.77],[-1.201,-2.072],[-1.792,-3.268],[-1.259,-2.323],[-0.291,-0.939],[-0.483,-3.827],[1.345,-1.848],[1.057,-0.733],[2.683,-1.495],[1.707,-0.935],[1.545,-0.843],[0.276,-0.155],[2.441,1.421],[1.915,1.099],[2.46,1.427],[0.652,0.397],[0.591,0.521],[-3.897,1.98],[-0.905,0.224],[-0.164,0.028],[-1.451,-0.818],[-1.54,-0.887],[-0.097,-0.055],[-2.084,1.109],[-1.302,0.704],[-1.975,1.369],[-0.31,1.632],[1.003,2.012],[2.436,4.239],[0.921,1.561]],"v":[[73.226,161.642],[75.295,158.122],[77.848,153.701],[78.405,153.41],[84.191,152.825],[95.213,150.555],[95.488,150.63],[73.293,188.776],[72.094,186.865],[66.641,177.903],[61.437,169.116],[56.539,160.8],[53.013,154.539],[47.683,144.709],[44.453,137.497],[43.905,134.581],[46.988,124.46],[51.811,119.717],[55.145,117.754],[63.212,113.304],[68.348,110.523],[72.97,107.971],[73.732,107.973],[81.068,112.215],[86.825,115.489],[94.171,119.824],[95.96,121.286],[97.72,122.926],[85.716,127.248],[82.965,127.778],[82.447,127.68],[78.11,125.2],[73.488,122.543],[73.092,122.576],[66.851,125.923],[62.975,128.08],[59.013,133.684],[59.777,138.262],[62.931,144.226],[70.345,156.883]],"c":true},"ix":2},"nm":"Path 1","mn":"ADBE Vector Shape - Group","hd":false},{"ty":"st","c":{"a":0,"k":[1,1,1,1],"ix":3},"o":{"a":0,"k":100,"ix":4},"w":{"a":0,"k":0,"ix":5},"lc":1,"lj":1,"ml":4,"bm":0,"nm":"Stroke 1","mn":"ADBE Vector Graphic - Stroke","hd":false},{"ty":"fl","c":{"a":0,"k":[0.643137254902,0.811764765721,0.215686289469,1],"ix":4},"o":{"a":0,"k":100,"ix":5},"r":1,"bm":0,"nm":"Fill 1","mn":"ADBE Vector Graphic - Fill","hd":false},{"ty":"tr","p":{"a":0,"k":[0,0],"ix":2},"a":{"a":0,"k":[0,0],"ix":1},"s":{"a":0,"k":[100,100],"ix":3},"r":{"a":0,"k":0,"ix":6},"o":{"a":0,"k":100,"ix":7},"sk":{"a":0,"k":0,"ix":4},"sa":{"a":0,"k":0,"ix":5},"nm":"Transform"}],"nm":"Shape 1","np":3,"cix":2,"bm":0,"ix":1,"mn":"ADBE Vector Group","hd":false}],"ip":0,"op":2756.241112264,"st":0,"bm":0},{"ddd":0,"ind":27,"ty":4,"nm":"green4","sr":1,"ks":{"o":{"a":1,"k":[{"i":{"x":[0.833],"y":[1]},"o":{"x":[0.333],"y":[0]},"t":57,"s":[0]},{"t":58.0000023623884,"s":[100]}],"ix":11},"r":{"a":0,"k":0,"ix":10},"p":{"a":0,"k":[373.168,547.322,0],"ix":2},"a":{"a":0,"k":[72.603,154.838,0],"ix":1},"s":{"a":0,"k":[151.293,151.293,100],"ix":6}},"ao":0,"shapes":[{"ty":"gr","it":[{"ind":0,"ty":"sh","ix":1,"ks":{"a":0,"k":{"i":[[-0.288,0.182],[0.387,-0.88],[1.319,-2.602],[1.687,-3.069],[1.347,-2.378],[1.645,-2.875],[1.546,-2.673],[1.713,-2.942],[2.043,-3.485],[1.701,-2.885],[1.931,-3.269],[1.661,-2.778],[0.117,-0.1],[0.217,0.356],[2.17,3.561],[1.992,3.297],[1.694,2.844],[1.502,2.544],[1.224,2.101],[1.484,2.578],[1.131,2.004],[1.531,2.746],[0.77,1.478],[2.108,4.229],[0.676,3.164],[0.105,0.932],[0.025,0.884],[-0.13,0.72],[-0.453,1.555],[-2.021,2.705],[-1.843,1.72],[-2.143,1.142],[-3.192,1.771],[-2.388,1.33],[-3.307,1.832],[-2.33,1.281],[-0.279,0.189],[-0.363,-0.211],[-1.819,-1.042],[-2.132,-1.209],[-1.789,-1.017],[-2.096,-1.197],[-1.513,-0.861],[-2.055,-1.115],[-1.686,-1.531],[-0.701,-0.641],[3.892,-2.697],[0.622,0.615],[2.276,1.21],[1.831,1.057],[1.668,0.964],[1.864,1.074],[1.656,0.949],[0.914,0.528],[1.734,-0.96],[2.355,-1.312],[2.786,-1.539],[1.948,-1.118],[0.767,-0.626],[0.796,-0.834],[1.18,-2.466],[0.239,-1.98],[-0.64,-2.214],[-0.737,-1.711],[-0.845,-1.588],[-1.955,-3.542],[-1.506,-2.609],[-1.677,-2.854],[-1.661,-2.777],[-1.707,-2.814],[-1.561,-2.553],[-1.141,-1.84],[-0.431,0.73],[-1.599,2.727],[-1.251,2.15],[-1.62,2.802],[-1.528,2.682],[-2.019,3.566],[-1.439,2.584],[-0.87,1.463],[-0.37,0.193],[-2.161,1.198],[-1.56,1.063],[-1.722,1.262]],"o":[[-0.353,1.08],[-1.173,2.673],[-1.583,3.123],[-1.317,2.396],[-1.632,2.882],[-1.533,2.679],[-1.704,2.947],[-2.033,3.492],[-1.693,2.888],[-1.928,3.27],[-1.646,2.786],[-0.028,0.046],[-0.235,-0.361],[-2.17,-3.561],[-2.005,-3.29],[-1.712,-2.834],[-1.512,-2.539],[-1.236,-2.094],[-1.497,-2.571],[-1.148,-1.994],[-1.546,-2.738],[-0.811,-1.456],[-2.182,-4.192],[-1.433,-2.876],[-0.195,-0.915],[-0.099,-0.879],[-0.021,-0.735],[0.288,-1.597],[0.949,-3.254],[1.52,-2.034],[1.757,-1.639],[3.221,-1.716],[2.39,-1.326],[3.303,-1.84],[2.326,-1.288],[0.295,-0.163],[0.378,-0.256],[1.811,1.054],[2.127,1.218],[1.79,1.015],[2.098,1.193],[1.512,0.863],[2.032,1.157],[2.02,1.096],[0.632,0.574],[-3.096,3.516],[-0.605,-0.624],[-1.831,-1.807],[-1.866,-0.993],[-1.669,-0.964],[-1.863,-1.076],[-1.654,-0.952],[-0.909,-0.521],[-1.719,0.941],[-2.358,1.306],[-2.781,1.548],[-1.966,1.086],[-0.857,0.492],[-0.894,0.729],[-1.874,1.962],[-0.849,1.776],[-0.278,2.306],[0.516,1.785],[0.712,1.652],[1.901,3.571],[1.456,2.637],[1.654,2.868],[1.639,2.79],[1.689,2.824],[1.552,2.558],[1.082,1.77],[0.458,-0.779],[1.609,-2.721],[1.258,-2.146],[1.628,-2.798],[1.545,-2.673],[2.028,-3.56],[1.457,-2.574],[0.829,-1.488],[0.193,-0.325],[2.191,-1.144],[1.65,-0.914],[1.763,-1.202],[0.128,-0.094]],"v":[[123.77,135.795],[122.803,138.704],[119.163,146.667],[114.154,155.903],[110.164,163.066],[105.227,171.689],[100.63,179.729],[95.479,188.548],[89.389,199.027],[84.263,207.666],[78.499,217.489],[73.524,225.825],[73.323,226],[72.634,224.94],[66.13,214.254],[60.112,204.387],[55.027,195.855],[50.492,188.239],[46.819,181.936],[42.332,174.222],[38.932,168.213],[34.3,159.995],[31.934,155.59],[25.428,142.994],[22.055,133.993],[21.665,131.207],[21.445,128.56],[21.563,126.352],[22.58,121.59],[27.263,112.763],[32.399,107.215],[38.205,102.978],[47.795,97.693],[54.957,93.7],[64.868,88.184],[71.859,84.343],[72.732,83.832],[73.803,83.876],[79.251,87.014],[85.638,90.658],[91.018,93.688],[97.302,97.286],[101.845,99.863],[107.943,103.33],[113.384,107.412],[115.347,109.203],[105.032,118.596],[103.207,116.718],[97.037,112.221],[91.539,109.058],[86.531,106.171],[80.945,102.937],[75.976,100.094],[73.247,98.52],[68.052,101.366],[60.987,105.302],[52.642,109.943],[46.735,113.184],[44.303,114.897],[41.74,117.228],[37.002,123.773],[35.279,129.371],[35.717,136.179],[37.695,141.407],[40.049,146.267],[45.842,156.932],[50.296,164.797],[55.314,173.368],[60.245,181.73],[65.364,190.173],[70.023,197.846],[73.348,203.213],[74.666,200.973],[79.492,192.81],[83.23,186.351],[88.126,177.965],[92.72,169.923],[98.798,159.238],[103.139,151.5],[105.616,147.031],[106.644,146.326],[113.223,142.905],[118.04,139.924],[123.214,136.148]],"c":true},"ix":2},"nm":"Path 1","mn":"ADBE Vector Shape - Group","hd":false},{"ty":"st","c":{"a":0,"k":[1,1,1,1],"ix":3},"o":{"a":0,"k":100,"ix":4},"w":{"a":0,"k":0,"ix":5},"lc":1,"lj":1,"ml":4,"bm":0,"nm":"Stroke 1","mn":"ADBE Vector Graphic - Stroke","hd":false},{"ty":"fl","c":{"a":0,"k":[0.007843137255,0.450980422076,0.207843152214,1],"ix":4},"o":{"a":0,"k":100,"ix":5},"r":1,"bm":0,"nm":"Fill 1","mn":"ADBE Vector Graphic - Fill","hd":false},{"ty":"tr","p":{"a":0,"k":[0,0],"ix":2},"a":{"a":0,"k":[0,0],"ix":1},"s":{"a":0,"k":[100,100],"ix":3},"r":{"a":0,"k":0,"ix":6},"o":{"a":0,"k":100,"ix":7},"sk":{"a":0,"k":0,"ix":4},"sa":{"a":0,"k":0,"ix":5},"nm":"Transform"}],"nm":"Shape 1","np":3,"cix":2,"bm":0,"ix":1,"mn":"ADBE Vector Group","hd":false}],"ip":0,"op":2756.241112264,"st":0,"bm":0}]}],"layers":[{"ddd":0,"ind":1,"ty":4,"nm":"Layer 1/typo_karbar_json Outlines","sr":1,"ks":{"o":{"a":1,"k":[{"i":{"x":[0.667],"y":[1]},"o":{"x":[0.333],"y":[0]},"t":68,"s":[0]},{"t":109.000004439661,"s":[100]}],"ix":11},"r":{"a":0,"k":0,"ix":10},"p":{"a":0,"k":[375,795,0],"ix":2},"a":{"a":0,"k":[240.5,88,0],"ix":1},"s":{"a":0,"k":[64,64,100],"ix":6}},"ao":0,"shapes":[{"ty":"gr","it":[{"ind":0,"ty":"sh","ix":1,"ks":{"a":0,"k":{"i":[[0,0],[0,0],[0,0],[1.479,-2.239],[0,0],[0,0],[2.68,0],[0,0],[0,-4.411],[0,0],[0,0],[3.06,0],[0,0],[1.34,-2.76],[0,0],[0,0],[4.42,0],[0,0],[0,-4.411],[0,0],[0,0],[4.06,0],[0,0],[0,-4.41],[0,0],[-0.979,-2.26],[-1.649,-1.66],[-2.18,-0.95],[-2.031,-0.15],[1.561,-2.541],[0.2,0.199],[6.9,0],[22.901,0.2],[2.799,-0.7],[2.8,-7.599],[-0.699,-4.6],[-7.6,-3.899],[-4.6,0],[0,0],[0,-1.2],[0,0],[0.429,-0.749],[4.9,-3],[2.1,0],[0,0],[2.3,-0.2],[4.199,-6.699],[-0.7,-5.8],[-9.501,-3.5],[-3.901,0],[0,0],[-6.5,3.5],[-0.699,-0.501],[-5.999,-0.2],[-9.3,-0.2],[-3.501,0.5],[-10.2,5.999],[-0.7,-0.5],[-0.201,-1.399],[-2.3,-1.4],[-2.8,0],[0,0],[-1.9,0.499],[-0.9,3.9],[-0.701,1.199],[-13.9,-0.499],[-11.8,7.6],[-0.2,-0.899],[-0.501,-0.7],[-3.899,0],[-11.6,0.201],[-2.3,3.901],[-0.499,1.6],[-0.899,-0.5],[-1.9,-0.7],[-16.4,3.001],[-10.199,11.299],[-3.5,11.6],[0,3.201],[0,0],[2.501,3.5],[7.9,0],[0,0],[1.2,0.901],[2.1,0.901],[2.561,0.12],[-0.69,1.569],[0,2.55],[0,0],[0.979,2.27],[1.66,1.67],[2.21,0.949],[2.51,0],[0,0],[1.43,-2.181],[1.359,0.579],[2.509,0],[0,0],[2.271,-0.99],[1.66,-1.659],[0.36,-0.43],[0.39,0.4],[2.21,0.949],[2.51,0],[0,0],[0,0]],"o":[[0,0],[0,0],[-2.681,0],[0,0],[0,0],[-1.479,-2.239],[0,0],[-4.42,0],[0,0],[0,0],[-1.341,-2.76],[0,0],[-3.069,0],[0,0],[0,0],[0,-4.411],[0,0],[-4.41,0],[0,0],[0,0],[-0.51,-3.931],[0,0],[-4.42,0],[0,0],[0,2.55],[0.95,2.18],[1.661,1.649],[1.841,0.79],[-2.011,1.81],[-0.399,-0.2],[-5.1,-4.8],[-22.901,0.2],[-2.8,0],[-7.4,1.8],[-1.8,4.401],[1.201,8.3],[4.1,2.301],[0,0],[0.9,0],[0,0],[0,0.9],[-2.5,5.401],[-1.9,0.9],[0,0],[-2.299,0],[-7.7,1.099],[-3.001,5.101],[1.2,10.2],[3.699,1.399],[0,0],[7.4,0],[0.7,-0.501],[5.1,3.199],[9.1,0.2],[3.501,0.199],[11.6,-1.8],[0.201,-0.302],[0,1.4],[0.499,2.801],[2.6,1.6],[0,0],[2.1,0],[4.101,-0.9],[0.199,-0.9],[11.999,7.399],[13.9,0.501],[0.7,0.9],[0.3,0.701],[2.299,3.7],[11.301,0.201],[4.201,-0.199],[0.901,-1.599],[0.201,-0.901],[1.601,0.899],[15.201,7],[14.8,-2.8],[8.1,-9.3],[1,-3.2],[0,0],[0,-4.199],[-4.9,-6.2],[0,0],[-1.4,0],[-1.799,-1.599],[-2.03,-0.729],[1.06,-1.311],[0.979,-2.27],[0,0],[0,-2.509],[-0.951,-2.22],[-1.67,-1.66],[-2.269,-0.97],[0,0],[-2.8,0],[-1.161,-0.851],[-2.271,-0.97],[0,0],[-2.56,0],[-2.18,0.939],[-0.4,0.391],[-0.36,-0.43],[-1.67,-1.66],[-2.269,-0.97],[0,0],[0,0],[0,0]],"v":[[-11.99,-87.501],[-11.99,-87.49],[-15.649,-87.49],[-22.319,-83.901],[-27.829,-75.57],[-33.35,-83.901],[-40.02,-87.49],[-46.98,-87.49],[-54.98,-79.49],[-54.98,-66.38],[-63.019,-82.97],[-70.22,-87.49],[-78.28,-87.49],[-85.48,-82.97],[-88.99,-75.721],[-88.99,-79.49],[-96.99,-87.49],[-103.959,-87.49],[-111.959,-79.49],[-111.959,-59.63],[-113.43,-59.63],[-121.36,-66.6],[-128.329,-66.6],[-136.33,-58.6],[-136.33,-55.111],[-134.85,-47.85],[-130.93,-42.07],[-125.15,-38.149],[-119.329,-36.73],[-124.7,-30.2],[-125.6,-30.9],[-143.899,-37.799],[-212.7,-37.799],[-221.299,-36.9],[-237.3,-23.501],[-238.9,-9.799],[-225.9,8.7],[-212.499,11.701],[-168.8,11.701],[-167.4,13.1],[-167.4,20.701],[-168.039,23.28],[-179.4,35.501],[-185,36.901],[-211.2,36.901],[-217.9,37.401],[-235.999,48.5],[-239.2,65.201],[-223.199,85.601],[-211.399,87.201],[-178.499,87.201],[-157.9,82.301],[-155.8,82.301],[-139.1,86.901],[-111.5,87.101],[-100.799,86.401],[-67.7,75.102],[-66.3,74.601],[-65.599,78.8],[-61.4,85.101],[-53.5,87.201],[-21.5,87.201],[-15.7,86.501],[-8.099,79.101],[-7.199,76.101],[31.7,87],[70.6,76.801],[71.5,79.8],[72.701,82.101],[82.9,87],[117.4,87],[127.6,81.7],[129,77.101],[130.4,76.401],[135.5,78.901],[183.4,84.5],[220.9,63.201],[238,31.901],[239.9,22.2],[239.9,-16.201],[236,-27.799],[217,-37.499],[138.3,-37.499],[134.8,-38.701],[128.8,-42.201],[121.82,-43.519],[124.451,-47.85],[125.93,-55.111],[125.93,-69.041],[124.461,-76.24],[120.53,-82.09],[114.69,-86.02],[107.48,-87.49],[83.11,-87.49],[76.411,-83.86],[72.631,-86.02],[65.421,-87.49],[51.5,-87.49],[44.23,-86],[38.45,-82.081],[37.32,-80.841],[36.19,-82.09],[30.35,-86.02],[23.14,-87.49],[4.671,-87.49],[4.671,-87.501]],"c":true},"ix":2},"nm":"Path 1","mn":"ADBE Vector Shape - Group","hd":false},{"ind":1,"ty":"sh","ix":2,"ks":{"a":0,"k":{"i":[[0,0],[0,0],[-1.281,-0.55],[-0.951,-0.94],[-0.551,-1.28],[0,-1.43],[0,0],[0.54,-1.259],[0.938,-0.949],[1.279,-0.55],[1.431,0],[0,0]],"o":[[0,0],[1.431,0],[1.279,0.55],[0.938,0.95],[0.54,1.279],[0,0],[0,1.459],[-0.551,1.261],[-0.951,0.951],[-1.281,0.55],[0,0],[0,0]],"v":[[83.201,-79.44],[107.6,-79.44],[111.661,-78.62],[115.001,-76.38],[117.241,-73.04],[118.06,-68.981],[118.06,-55.04],[117.241,-50.961],[115.001,-47.651],[111.661,-45.41],[107.6,-44.59],[83.201,-44.59]],"c":true},"ix":2},"nm":"Path 2","mn":"ADBE Vector Shape - Group","hd":false},{"ind":2,"ty":"sh","ix":3,"ks":{"a":0,"k":{"i":[[1.26,0.55],[0.94,0.951],[0.54,1.261],[0,1.459],[0,0],[-0.55,1.279],[-0.95,0.95],[-1.261,0.55],[-1.459,0],[0,0],[-1.279,-0.55],[-0.95,-0.94],[-0.55,-1.28],[0,-1.43],[0,0],[0.54,-1.259],[0.94,-0.949],[1.28,-0.55],[1.429,0],[0,0]],"o":[[-1.261,-0.55],[-0.95,-0.949],[-0.55,-1.259],[0,0],[0,-1.43],[0.54,-1.28],[0.94,-0.94],[1.26,-0.55],[0,0],[1.429,0],[1.28,0.55],[0.94,0.95],[0.54,1.279],[0,0],[0,1.459],[-0.55,1.261],[-0.95,0.951],[-1.279,0.55],[0,0],[-1.459,0]],"v":[[47.411,-45.41],[44.1,-47.651],[41.86,-50.961],[41.041,-55.04],[41.041,-68.981],[41.86,-73.04],[44.1,-76.38],[47.411,-78.62],[51.49,-79.44],[65.431,-79.44],[69.49,-78.62],[72.83,-76.38],[75.07,-73.04],[75.89,-68.981],[75.89,-55.04],[75.07,-50.961],[72.83,-47.651],[69.49,-45.41],[65.431,-44.59],[51.49,-44.59]],"c":true},"ix":2},"nm":"Path 3","mn":"ADBE Vector Shape - Group","hd":false},{"ind":3,"ty":"sh","ix":4,"ks":{"a":0,"k":{"i":[[0,0],[0,0],[-1.28,-0.55],[-0.95,-0.94],[-0.55,-1.28],[0,-1.43],[0.479,-1.17],[0.861,-0.931],[-0.491,-1.18],[0,-1.36],[0.54,-1.259],[0.941,-0.949],[1.28,-0.55],[1.43,0],[0,0]],"o":[[0,0],[1.43,0],[1.28,0.55],[0.941,0.95],[0.54,1.279],[0,1.361],[-0.491,1.179],[0.861,0.93],[0.479,1.18],[0,1.459],[-0.55,1.261],[-0.95,0.951],[-1.28,0.55],[0,0],[0,0]],"v":[[-1.22,-79.44],[23.17,-79.44],[27.23,-78.62],[30.57,-76.38],[32.81,-73.04],[33.63,-68.981],[32.911,-65.18],[30.89,-62.01],[32.911,-58.85],[33.63,-55.04],[32.81,-50.961],[30.57,-47.651],[27.23,-45.41],[23.17,-44.59],[-1.22,-44.59]],"c":true},"ix":2},"nm":"Path 4","mn":"ADBE Vector Shape - Group","hd":false},{"ind":4,"ty":"sh","ix":5,"ks":{"a":0,"k":{"i":[[0,0],[0,0],[0,0],[0,0],[0,0],[0,0],[0,0],[0,0],[0,0],[0,0],[0,0],[0,0]],"o":[[0,0],[0,0],[0,0],[0,0],[0,0],[0,0],[0,0],[0,0],[0,0],[0,0],[0,0],[0,0]],"v":[[-15.78,-79.44],[-8.81,-79.44],[-8.81,-44.59],[-15.78,-44.59],[-15.78,-66.89],[-27.98,-48.47],[-40.18,-66.89],[-40.18,-44.59],[-47.149,-44.59],[-47.149,-79.44],[-40.18,-79.44],[-27.98,-61.021]],"c":true},"ix":2},"nm":"Path 5","mn":"ADBE Vector Shape - Group","hd":false},{"ind":5,"ty":"sh","ix":6,"ks":{"a":0,"k":{"i":[[0,0],[0,0],[0,0],[0,0],[0,0],[0,0],[0,0],[0,0],[0,0],[0,0],[0,0]],"o":[[0,0],[0,0],[0,0],[0,0],[0,0],[0,0],[0,0],[0,0],[0,0],[0,0],[0,0]],"v":[[-78.46,-79.44],[-70.389,-79.44],[-53.52,-44.59],[-61.03,-44.59],[-64.42,-51.56],[-74.079,-51.56],[-81.05,-58.531],[-67.8,-58.531],[-74.429,-72.22],[-87.82,-44.59],[-95.34,-44.59]],"c":true},"ix":2},"nm":"Path 6","mn":"ADBE Vector Shape - Group","hd":false},{"ind":6,"ty":"sh","ix":7,"ks":{"a":0,"k":{"i":[[0,0],[-0.68,0.681],[0,0.959],[0,0],[0,0],[0,0],[0.539,-1.259],[0.939,-0.949],[1.28,-0.55],[1.43,0],[0,0],[1.27,0.55],[0.951,0.951],[0.55,1.261],[0,1.459],[0,0],[0,0],[0,0],[-0.68,-0.679],[-0.969,0]],"o":[[0.96,0],[0.68,-0.679],[0,0],[0,0],[0,0],[0,1.459],[-0.551,1.261],[-0.951,0.951],[-1.281,0.55],[0,0],[-1.46,0],[-1.26,-0.55],[-0.939,-0.949],[-0.54,-1.259],[0,0],[0,0],[0,0],[0,0.959],[0.68,0.681],[0,0]],"v":[[-107.66,-51.56],[-105.19,-52.581],[-104.169,-55.04],[-104.169,-79.44],[-97.199,-79.44],[-97.199,-55.04],[-98.019,-50.961],[-100.259,-47.651],[-103.599,-45.41],[-107.66,-44.59],[-118.11,-44.59],[-122.2,-45.41],[-125.51,-47.651],[-127.75,-50.961],[-128.57,-55.04],[-128.57,-58.531],[-121.599,-58.531],[-121.599,-55.04],[-120.58,-52.581],[-118.11,-51.56]],"c":true},"ix":2},"nm":"Path 7","mn":"ADBE Vector Shape - Group","hd":false},{"ind":7,"ty":"sh","ix":8,"ks":{"a":0,"k":{"i":[[-0.5,2.599],[-5.6,1.8],[-5.8,-4.2],[-0.94,-1.709],[0.511,-3.39],[2.15,-2.519],[0.96,-0.801],[1.05,-0.451],[1.08,-0.241],[0.8,-0.099],[0.4,0.01],[0.19,0.04],[0.071,0],[-2.06,4.601],[-0.349,1.08],[0.12,0.59],[0.89,0],[0,0]],"o":[[0.9,-6],[6.301,-1.9],[1.581,1.14],[1.67,3.03],[-0.49,3.28],[-0.81,0.95],[-0.88,0.729],[-1.02,0.429],[-0.791,0.17],[-0.39,0.061],[-0.19,-0.009],[-0.06,-0.011],[3.5,-3.51],[0.46,-1.029],[0.191,-0.55],[-0.24,-1.221],[0,0],[-2.5,0]],"v":[[-116.3,-20.1],[-106.3,-32.1],[-88,-29.1],[-84.15,-24.831],[-82.61,-14.39],[-86.73,-5.531],[-89.4,-2.9],[-92.24,-1.1],[-95.409,-0.14],[-97.78,0.329],[-98.97,0.41],[-99.53,0.351],[-100.09,0.201],[-90.68,-11.331],[-89.4,-14.45],[-89.08,-16.27],[-92.2,-17.301],[-114,-17.301]],"c":true},"ix":2},"nm":"Path 8","mn":"ADBE Vector Shape - Group","hd":false},{"ind":8,"ty":"sh","ix":9,"ks":{"a":0,"k":{"i":[[1.596,0.127],[10.401,8.601],[3.7,6.7],[1.29,6.431],[-0.06,3.479],[0.021,3.519],[-0.081,7.19],[-0.01,0.861],[-7.399,-3.7],[-1,-2.1],[0,-2.999],[0,0],[-2.1,-4.6],[-5.301,-3.199],[-5.5,-0.501],[-5,1.9],[-3.771,4.8],[-1.06,2.11],[-0.41,1.72],[0,1.87],[0,0],[3,0],[0,0],[0,6.4],[0,0],[-2.3,0],[-11.599,0],[0,0],[0,-7.401],[0,0],[1.629,-4.58],[2.191,-3.849],[5.46,-4.71],[9,-2],[4.676,0]],"o":[[-13.399,-0.7],[-5.999,-4.899],[-3.159,-5.73],[-0.68,-3.439],[0.061,-3.521],[-0.03,-7.191],[0.009,-0.861],[0.201,-12.699],[2.301,1.201],[1.201,2.5],[0,0],[0,5.101],[2.5,5.601],[4.599,3.001],[5.3,0.499],[5.7,-2.16],[1.46,-1.86],[0.78,-1.54],[0.431,-1.84],[0,0],[0,-2.999],[0,0],[-6.501,0],[0,0],[0,-2.3],[11.399,-0.2],[0,0],[7.4,0],[0,0],[0,4.889],[-1.49,4.159],[-3.559,6.271],[-6.9,6],[-4.705,1.045],[-1.586,0]],"v":[[164.4,74.5],[128.3,61.299],[113.9,44.201],[107.32,26.299],[106.48,15.491],[106.44,4.941],[106.471,-16.63],[106.5,-19.201],[126.9,-31.501],[131.8,-26.4],[133.9,-18.301],[133.9,13.2],[136.9,27.799],[148.201,41.2],[163.701,46.301],[179.4,44.401],[193.96,33.881],[197.74,27.891],[199.69,22.98],[200,17.411],[200,4.999],[197.201,2.201],[159.701,2.201],[147.701,-9.799],[147.701,-24.4],[150.001,-26.7],[184.3,-26.9],[217.2,-26.9],[229.501,-14.6],[229.501,18.23],[226.581,32.391],[221.09,44.46],[207.5,61.101],[183.201,73.101],[169.171,74.69]],"c":true},"ix":2},"nm":"Path 9","mn":"ADBE Vector Shape - Group","hd":false},{"ind":9,"ty":"sh","ix":10,"ks":{"a":0,"k":{"i":[[-0.476,0],[0,0],[-4.8,3.399],[-2.4,5.1],[-0.501,4.399],[-0.2,5.389],[-0.02,5.37],[0,2.109],[-3.801,1.8],[-3.899,-0.9],[-1.7,-2.1],[-1.8,0],[0,0],[-2.1,-1.1],[-0.2,-6],[0.111,-10.199],[1.601,-3.899],[5.401,-6.701],[12,-3.4],[4.1,0],[7.399,1.899],[7.6,8.299],[2.8,7.2],[0.9,7.2],[0,3.899],[2.301,0],[0,0],[0,-1.1],[0,0],[3.7,-9.799],[15.499,-6.701],[8.6,-1.201],[0,0],[2.5,0.7],[2.299,5.102],[0,0],[6.5,-1.1],[2.299,0],[0,0],[2.299,0.901],[1.399,3.7],[-0.7,3],[-6.201,0.701],[-1.399,0],[-8.4,-0.2],[-5.6,4.899],[-2.401,4.4],[0,2.999],[0,0],[2.801,0],[0,0],[2.301,0.7],[0.3,6],[-1.601,2.299],[-4.201,0.5],[-1.599,0],[0,0],[-1.9,-0.199],[-1.099,-6.399],[0,-2.301],[0,0],[-1.46,0]],"o":[[0,0],[6,0],[4.4,-3.2],[1.9,-4.2],[0.609,-5.371],[0.19,-5.36],[0.01,-2.11],[0,-4.4],[3.499,-1.6],[2.1,0.5],[1.2,1.601],[0,0],[2.299,0],[5.299,2.801],[0.2,10.2],[-0.04,3.881],[-3,8.101],[-7.6,9.7],[-3.899,1.199],[-7.6,0.201],[-10.901,-2.799],[-5.3,-5.8],[-2.5,-6.899],[-0.499,-3.901],[0,-2.3],[0,0],[-1.2,0],[0,0],[0.7,10.199],[-5.801,16.001],[-7.901,3.5],[0,0],[-2.5,0],[-4.399,-1.699],[0,0],[-3.899,5.3],[-2.299,0.5],[0,0],[-2.8,0],[-3.701,-1.399],[-0.901,-2.8],[1.2,-6.7],[1.199,-0.2],[8.3,0],[7.6,0.201],[3.7,-3.5],[1.399,-2.501],[0,0],[0,-2.8],[0,0],[-2.3,0],[-5.6,-1.899],[0,-2.8],[2.499,-3.901],[1.399,-0.2],[0,0],[1.601,0],[5.799,1.201],[0.2,2.101],[0,0],[0,2.306],[0.313,0]],"v":[[-124.6,46.901],[-101.2,46.901],[-84.8,41.601],[-74.8,29.101],[-71.099,16.4],[-70.43,-0.1],[-70.41,-15.859],[-70.4,-22.2],[-64.099,-31.2],[-52.8,-32.4],[-46.5,-28.701],[-41.9,-26.799],[81.001,-26.799],[87.301,-25.201],[95.6,-11.799],[95.1,18.799],[92.1,31.299],[79.8,53.501],[50.4,73.601],[38.4,75.5],[15.701,73.401],[-12.3,57.201],[-24.1,37.5],[-29.2,16.201],[-29.699,4.4],[-32,2.101],[-42.7,2.101],[-44.3,3.701],[-44.3,5.801],[-48.699,35.7],[-80.899,69.501],[-105.9,76.001],[-138.3,76.001],[-145.9,74.8],[-155.599,65.5],[-156.3,66.201],[-172.3,75.201],[-179.199,75.701],[-213,75.701],[-220.599,74.3],[-227.999,66.701],[-228.5,57.901],[-215.999,47.5],[-212.1,47.5],[-187.3,47.5],[-167.8,40.101],[-158.499,28.301],[-156.599,20.201],[-156.599,3.299],[-159.4,0.499],[-212.4,0.499],[-219.1,-0.201],[-228.4,-12.701],[-226.799,-20.6],[-216.099,-26.4],[-211.7,-26.4],[-143.8,-26.4],[-138.699,-26.201],[-127.6,-13.501],[-127.099,-6.999],[-127.099,44.401],[-125.775,46.91]],"c":true},"ix":2},"nm":"Path 10","mn":"ADBE Vector Shape - Group","hd":false},{"ind":10,"ty":"sh","ix":11,"ks":{"a":0,"k":{"i":[[-0.401,2.299],[-5.301,2.499],[-6.5,-3.201],[-0.9,-4.7],[-0.16,-0.821],[0.66,-0.29],[0.29,0],[0,0],[4.2,0],[0,0]],"o":[[0.699,-5.8],[6.5,-3.001],[4.4,2.099],[0.161,0.83],[0.11,0.599],[-0.27,0.119],[0,0],[-4.001,0.1],[0,0],[-2.3,0]],"v":[[-55.099,73.201],[-46.099,60.501],[-26.4,60.701],[-18.8,71.401],[-18.31,73.911],[-18.82,75.461],[-19.7,75.601],[-24.299,75.601],[-36.6,75.701],[-53,75.701]],"c":true},"ix":2},"nm":"Path 11","mn":"ADBE Vector Shape - Group","hd":false},{"ind":11,"ty":"sh","ix":12,"ks":{"a":0,"k":{"i":[[-0.199,1.7],[-8.6,0.7],[-3.901,-2.701],[-0.5,-5.1],[1.6,0],[5.5,0],[0,0]],"o":[[1.4,-10],[4.9,-0.499],[4.2,3],[0,1.6],[-5.501,-0.2],[0,0],[-1.9,0]],"v":[[81.2,73.8],[98.1,58.5],[111.501,61.701],[118,74.001],[116.4,75.901],[99.801,75.701],[83.1,75.701]],"c":true},"ix":2},"nm":"Path 12","mn":"ADBE Vector Shape - Group","hd":false},{"ind":12,"ty":"sh","ix":13,"ks":{"a":0,"k":{"i":[[0,0],[0,0],[0,0],[-0.69,0.681],[0,0.959],[0,0],[0.68,0.679],[0.96,0]],"o":[[0,0],[0,0],[0.96,0],[0.68,-0.679],[0,0],[0,-0.969],[-0.69,-0.68],[0,0]],"v":[[90.181,-72.47],[90.181,-51.56],[107.6,-51.56],[110.07,-52.581],[111.09,-55.04],[111.09,-68.981],[110.07,-71.45],[107.6,-72.47]],"c":true},"ix":2},"nm":"Path 13","mn":"ADBE Vector Shape - Group","hd":false},{"ind":13,"ty":"sh","ix":14,"ks":{"a":0,"k":{"i":[[0,0],[0.679,-0.68],[0,-0.969],[0,0],[-0.681,-0.679],[-0.959,0],[0,0],[-0.68,0.681],[0,0.959],[0,0],[0.681,0.679],[0.959,0]],"o":[[-0.959,0],[-0.681,0.679],[0,0],[0,0.959],[0.679,0.681],[0,0],[0.959,0],[0.681,-0.679],[0,0],[0,-0.969],[-0.68,-0.68],[0,0]],"v":[[51.49,-72.47],[49.031,-71.45],[48.01,-68.981],[48.01,-55.04],[49.031,-52.581],[51.49,-51.56],[65.431,-51.56],[67.9,-52.581],[68.921,-55.04],[68.921,-68.981],[67.9,-71.45],[65.431,-72.47]],"c":true},"ix":2},"nm":"Path 14","mn":"ADBE Vector Shape - Group","hd":false},{"ind":14,"ty":"sh","ix":15,"ks":{"a":0,"k":{"i":[[0,0],[0,0],[0,0],[0,0],[-0.68,0.681],[0,0.959],[0.68,0.68],[0.97,0],[0,0],[0,0],[0,0],[-0.68,0.681],[0,0.961],[0.68,0.679],[0.97,0]],"o":[[0,0],[0,0],[0,0],[0.97,0],[0.68,-0.679],[0,-0.971],[-0.68,-0.68],[0,0],[0,0],[0,0],[0.97,0],[0.68,-0.679],[0,-0.969],[-0.68,-0.68],[0,0]],"v":[[5.751,-72.47],[5.751,-65.5],[5.751,-51.56],[23.17,-51.56],[25.64,-52.581],[26.66,-55.04],[25.64,-57.51],[23.17,-58.531],[12.72,-58.531],[5.751,-65.5],[23.17,-65.5],[25.64,-66.521],[26.66,-68.981],[25.64,-71.45],[23.17,-72.47]],"c":true},"ix":2},"nm":"Path 15","mn":"ADBE Vector Shape - Group","hd":false},{"ind":15,"ty":"sh","ix":16,"ks":{"a":0,"k":{"i":[[0,0],[0,-2.051],[0,-0.016],[0,0],[-3.201,-7],[-6.1,-3.2],[-6.899,0],[-5.101,3.701],[-2.798,7.399],[0,2.5],[-0.001,1.484],[0,3.158],[1.099,-0.201],[0,0],[10.6,0]],"o":[[-2.084,0],[0,0.016],[0,0],[0,7.4],[2.8,6.001],[6.3,3.5],[6.3,-0.201],[6.299,-4.599],[0.901,-2.3],[0.066,-1.509],[0.001,-3.039],[0,-1.199],[0,0],[-10.4,-0.201],[0,0]],"v":[[0.2,0.7],[-1.9,2.751],[-1.9,2.799],[-1.9,6.701],[2.501,28.499],[15.5,42.601],[35.6,47.001],[52.701,41.2],[65.899,22.9],[67.8,15.999],[67.889,11.52],[67.8,2.299],[66.201,0.9],[64.6,0.9],[32.9,0.7]],"c":true},"ix":2},"nm":"Path 16","mn":"ADBE Vector Shape - Group","hd":false},{"ty":"mm","mm":1,"nm":"Merge Paths 1","mn":"ADBE Vector Filter - Merge","hd":false},{"ty":"gf","o":{"a":0,"k":100,"ix":10},"r":1,"bm":0,"g":{"p":3,"k":{"a":0,"k":[0,0.643,0.812,0.216,0.5,0.325,0.631,0.212,1,0.008,0.451,0.208],"ix":9}},"s":{"a":0,"k":[0,-10],"ix":5},"e":{"a":0,"k":[0,90],"ix":6},"t":1,"nm":"Gradient Fill 1","mn":"ADBE Vector Graphic - G-Fill","hd":false},{"ty":"tr","p":{"a":0,"k":[240.15,87.75],"ix":2},"a":{"a":0,"k":[0,0],"ix":1},"s":{"a":0,"k":[100,100],"ix":3},"r":{"a":0,"k":0,"ix":6},"o":{"a":0,"k":100,"ix":7},"sk":{"a":0,"k":0,"ix":4},"sa":{"a":0,"k":0,"ix":5},"nm":"Transform"}],"nm":"Group 1","np":18,"cix":2,"bm":0,"ix":1,"mn":"ADBE Vector Group","hd":false}],"ip":0,"op":121.000004928431,"st":0,"bm":0},{"ddd":0,"ind":3,"ty":4,"nm":"Shape Layer 1","td":1,"sr":1,"ks":{"o":{"a":0,"k":100,"ix":11},"r":{"a":0,"k":0,"ix":10},"p":{"a":0,"k":[375,500,0],"ix":2},"a":{"a":0,"k":[0,0,0],"ix":1},"s":{"a":0,"k":[100,100,100],"ix":6}},"ao":0,"shapes":[{"ty":"gr","it":[{"ind":0,"ty":"sh","ix":1,"ks":{"a":0,"k":{"i":[[0,0],[18.254,36.508],[15.312,58.185],[-9.159,12.211],[-33.587,17.811],[-10,-1],[-12,-5],[-10,-9],[-6,-12],[-3,-16],[3,-10],[5.66,-13.746],[9,-13],[8,-13],[5.75,-9.25],[13,-12]],"o":[[0,0],[-24,-48],[-10,-38],[9,-12],[16.5,-8.75],[10,1],[12,5],[10,9],[6,12],[3,16],[-3,10],[-7,17],[-9,13],[-6.671,10.84],[-4.867,7.83],[-13,12]],"v":[[-6.5,184.5],[-96,41],[-133,-60],[-117,-141],[-64.25,-188.25],[-11,-203],[41,-196],[80,-176],[112,-144],[130,-94],[125,-32],[101,28],[69,86],[34,139],[10.75,179.75],[-44.75,236.5]],"c":false},"ix":2},"nm":"Path 1","mn":"ADBE Vector Shape - Group","hd":false},{"ty":"st","c":{"a":0,"k":[1,1,1,1],"ix":3},"o":{"a":0,"k":100,"ix":4},"w":{"a":0,"k":26,"ix":5},"lc":1,"lj":1,"ml":4,"bm":0,"nm":"Stroke 1","mn":"ADBE Vector Graphic - Stroke","hd":false},{"ty":"tr","p":{"a":0,"k":[0,0],"ix":2},"a":{"a":0,"k":[0,0],"ix":1},"s":{"a":0,"k":[100,100],"ix":3},"r":{"a":0,"k":0,"ix":6},"o":{"a":0,"k":100,"ix":7},"sk":{"a":0,"k":0,"ix":4},"sa":{"a":0,"k":0,"ix":5},"nm":"Transform"}],"nm":"Shape 1","np":3,"cix":2,"bm":0,"ix":1,"mn":"ADBE Vector Group","hd":false},{"ty":"tm","s":{"a":1,"k":[{"i":{"x":[0.723],"y":[1]},"o":{"x":[0.617],"y":[0]},"t":61,"s":[100]},{"t":101.000004113814,"s":[0]}],"ix":1},"e":{"a":0,"k":100,"ix":2},"o":{"a":0,"k":0,"ix":3},"m":1,"ix":2,"nm":"Trim Paths 1","mn":"ADBE Vector Filter - Trim","hd":false}],"ip":0,"op":121.000004928431,"st":0,"bm":0},{"ddd":0,"ind":4,"ty":4,"nm":"Logo Final Outlines","tt":1,"sr":1,"ks":{"o":{"a":0,"k":100,"ix":11},"r":{"a":0,"k":0,"ix":10},"p":{"a":0,"k":[374,491,0],"ix":2},"a":{"a":0,"k":[408.5,572,0],"ix":1},"s":{"a":0,"k":[36,36,100],"ix":6}},"ao":0,"shapes":[{"ty":"gr","it":[{"ind":0,"ty":"sh","ix":1,"ks":{"a":0,"k":{"i":[[0,-218.098],[-28.419,-68.127],[-70.075,-120.296],[-5.286,-7.928],[-19.809,0],[0,0],[-5.285,7.928],[-70.075,120.295],[-28.419,68.129],[0,0],[219.799,0]],"o":[[0,0],[28.419,68.129],[70.075,120.295],[5.285,7.928],[0,0],[19.809,0],[5.285,-7.928],[70.075,-120.296],[28.42,-68.127],[0,-218.098],[-219.8,0]],"v":[[-397.983,-171.729],[-363.685,-23.447],[-235.993,240.892],[-42.617,539.883],[-0.326,566.631],[0.326,566.631],[42.617,539.883],[235.991,240.892],[363.684,-23.447],[397.983,-171.729],[0,-566.631]],"c":true},"ix":2},"nm":"Path 1","mn":"ADBE Vector Shape - Group","hd":false},{"ind":1,"ty":"sh","ix":2,"ks":{"a":0,"k":{"i":[[0.1,0.135],[2.375,3.474],[40.306,69.193],[25.663,62.046],[2.799,6.709],[1.011,11.171],[-64.954,64.452],[-92.757,0],[-65.552,-65.044],[-0.499,-91.069],[20.11,-48.207],[2.851,-6.894],[61.483,-105.547],[81.445,-119.145],[0.654,-0.975],[0.118,-0.145]],"o":[[-0.651,-0.967],[-80.284,-117.44],[-61.483,-105.547],[-2.852,-6.894],[-22.646,-54.287],[0.537,-91.013],[65.552,-65.044],[92.756,0],[64.99,64.487],[-1.81,21.749],[-2.798,6.708],[-25.664,62.045],[-40.879,70.175],[-2.383,3.484],[-0.102,0.135],[-0.117,-0.144]],"v":[[-0.328,511.377],[-4.922,504.638],[-191.924,215.221],[-308.159,-22.695],[-316.616,-43.082],[-346.977,-173.8],[-245.495,-414.765],[-0.001,-515.631],[245.493,-414.765],[346.977,-173.653],[316.614,-43.081],[308.159,-22.695],[191.924,215.221],[4.941,504.609],[0.329,511.375],[-0.001,511.795]],"c":true},"ix":2},"nm":"Path 2","mn":"ADBE Vector Shape - Group","hd":false},{"ind":2,"ty":"sh","ix":3,"ks":{"a":0,"k":{"i":[[-0.027,0.038],[0.024,-0.035]],"o":[[-0.027,0.038],[0.024,-0.035]],"v":[[0.258,511.483],[0.182,511.593]],"c":true},"ix":2},"nm":"Path 3","mn":"ADBE Vector Shape - Group","hd":false},{"ty":"mm","mm":1,"nm":"Merge Paths 1","mn":"ADBE Vector Filter - Merge","hd":false},{"ty":"gf","o":{"a":0,"k":100,"ix":10},"r":1,"bm":0,"g":{"p":3,"k":{"a":0,"k":[0,0.643,0.812,0.216,0.5,0.325,0.631,0.212,1,0.008,0.451,0.208],"ix":9}},"s":{"a":0,"k":[0.988,-611.802],"ix":5},"e":{"a":0,"k":[-0.543,600.57],"ix":6},"t":1,"nm":"Gradient Fill 1","mn":"ADBE Vector Graphic - G-Fill","hd":false},{"ty":"tr","p":{"a":0,"k":[408.288,571.505],"ix":2},"a":{"a":0,"k":[0,0],"ix":1},"s":{"a":0,"k":[100,100],"ix":3},"r":{"a":0,"k":0,"ix":6},"o":{"a":0,"k":100,"ix":7},"sk":{"a":0,"k":0,"ix":4},"sa":{"a":0,"k":0,"ix":5},"nm":"Transform"}],"nm":"Group 1","np":5,"cix":2,"bm":0,"ix":1,"mn":"ADBE Vector Group","hd":false}],"ip":0,"op":121.000004928431,"st":0,"bm":0},{"ddd":0,"ind":6,"ty":0,"nm":"logo","refId":"comp_0","sr":1,"ks":{"o":{"a":0,"k":100,"ix":11},"r":{"a":0,"k":0,"ix":10},"p":{"a":0,"k":[375,0.5,0],"ix":2},"a":{"a":0,"k":[375,0,0],"ix":1},"s":{"a":0,"k":[100,100,100],"ix":6}},"ao":0,"w":750,"h":1334,"ip":5.00000020365417,"op":121.000004928431,"st":5.00000020365417,"bm":0},{"ddd":0,"ind":7,"ty":4,"nm":"White Outlines","sr":1,"ks":{"o":{"a":1,"k":[{"i":{"x":[0.667],"y":[1]},"o":{"x":[0.167],"y":[0]},"t":0,"s":[0]},{"i":{"x":[0.667],"y":[1]},"o":{"x":[0.333],"y":[0]},"t":69,"s":[0]},{"t":109.000004439661,"s":[100]}],"ix":11},"r":{"a":0,"k":0,"ix":10},"p":{"a":0,"k":[374,485,0],"ix":2},"a":{"a":0,"k":[426,594,0],"ix":1},"s":{"a":0,"k":[38,38,100],"ix":6}},"ao":0,"shapes":[{"ty":"gr","it":[{"ind":0,"ty":"sh","ix":1,"ks":{"a":0,"k":{"i":[[36.005,-129.5],[15.35,-33.766],[93.003,-136.662],[2.285,-3.331],[0.224,0.315],[0.081,0.114],[40.299,69.2],[-78.02,181.39],[-27.14,26.93],[-92.799,0],[-65.601,-65.1]],"o":[[-10.201,36.694],[-68.69,151.096],[-3.562,5.233],[-0.218,0.318],[-1.211,-1.706],[-80.3,-117.4],[-90.32,-155.09],[15.11,-35.13],[65.601,-65],[92.801,0],[102.07,101.293]],"v":[[333.757,-41.239],[294.773,65.024],[34.882,489.065],[18.416,513.203],[17.512,513.21],[13.07,506.775],[-173.93,217.375],[-291.741,-318.664],[-227.531,-412.625],[17.969,-513.524],[263.469,-412.625]],"c":true},"ix":2},"nm":"Path 1","mn":"ADBE Vector Shape - Group","hd":false},{"ty":"fl","c":{"a":0,"k":[1,1,1,1],"ix":4},"o":{"a":0,"k":100,"ix":5},"r":1,"bm":0,"nm":"Fill 1","mn":"ADBE Vector Graphic - Fill","hd":false},{"ty":"tr","p":{"a":0,"k":[407.931,599.424],"ix":2},"a":{"a":0,"k":[0,0],"ix":1},"s":{"a":0,"k":[100,100],"ix":3},"r":{"a":0,"k":0,"ix":6},"o":{"a":0,"k":100,"ix":7},"sk":{"a":0,"k":0,"ix":4},"sa":{"a":0,"k":0,"ix":5},"nm":"Transform"}],"nm":"Group 1","np":2,"cix":2,"bm":0,"ix":1,"mn":"ADBE Vector Group","hd":false}],"ip":0,"op":121.000004928431,"st":0,"bm":0}],"markers":[]}